Workbook

Sheet Read Me
A1: Model risk management package — workbook guide
A2: POLICY DEVELOPMENT DRAFT — NOT IN FORCE | Information verified to 25 July 2026
A4: Item | B4: Explanation
A5: Package status | B5: POLICY DEVELOPMENT DRAFT — NOT IN FORCE. This workbook, the draft CPS XXXX and the draft CPG XXXX are policy-development artefacts with no legal effect.
A6: As-of date | B6: 25 July 2026. Source status was checked on this date. Regulatory positions change; re-verify before relying on any status statement.
A7: Purpose | B7: Evidence base, comparator assessment, gap scoring, traceability and red-team audit trail for a proposed cross-industry prudential standard on model risk management.
A8: Scope of the comparison | B8: Eight authorities: APRA, the US OCC and Federal Reserve, the PRA, OSFI, the ECB/SSM, MAS, the BCBS and the FSB.
A9: How to use | B9: Start with Executive Summary, then Scoring Methodology so the numbers can be interpreted. Gap Assessment carries the scores; Areas for Improvement is the prioritised output. Regulatory Crosswalk compares by domain; Requirement Test challenges each drafted requirement authority by authority. Red Team Audit records every correction.
A10: What the scoring measures | B10: How well the CURRENT Australian prudential framework addresses each model risk domain, against the strongest comparator practice. It does not score entity maturity and does not rank the comparator authorities against one another.
A11: Legal caution | B11: An overseas instrument is not binding in Australia whatever its status at home. Several of the most influential model risk instruments — including the US interagency guidance and PRA SS1/23 — are supervisory guidance rather than law even in their home jurisdiction. The Legal Status Matrix records this for each source.
A12: Provenance labels | B12: Extracted = close reflection of an explicit source requirement. Extracted + inferred = faithful synthesis across sources. Inferred = reasoned construction. Policy choice = proposed by the drafter, not directly mandated by any comparator. 'Policy choice' does not mean unsupported.
A13: Verification labels | B13: Verified — primary source: confirmed from the issuing authority's own document. Verified — secondary source: confirmed only from a reputable third party. Unverified: could not be confirmed and is not relied upon for any statement of requirement.
A14: Editable cells | B14: Blue text on a yellow fill marks an input you may change — domain weights and the priority band thresholds on Scoring Methodology. Everything downstream recalculates.
A15: Reproducibility | B15: Every artefact in this package is generated by the scripts in the build/ directory of the source repository, and can be regenerated or re-verified through the accompanying MCP server.

Sheet Executive Summary
A1: Executive summary
A2: POLICY DEVELOPMENT DRAFT — NOT IN FORCE | Counts are formulas linked to the detailed sheets.
A4: Metric | B4: Value | C4: Interpretation
A5: Draft mandatory requirements | B5: =COUNTA('Requirements Register'!A5:A200) -> 45 | C5: Bold mandatory paragraphs in draft CPS XXXX.
A6: Requirements that are policy choices | B6: =COUNTIF('Requirements Register'!I5:I200,"Yes") -> 5 | C6: Proposed by the drafter rather than mandated by a comparator. Require consultation and cost-benefit testing.
A7: Requirements flagged for legal settlement | B7: =COUNTIF('Requirements Register'!J5:J200,"Yes") -> 7 | C7: Carry an express legal-drafting reservation.
A8: Guidance paragraphs in draft CPG XXXX | B8: =COUNTA(Traceability!A5:A200) -> 146 | C8: Every requirement has at least one supporting guidance paragraph.
A9: Domains assessed | B9: =COUNTA('Gap Assessment'!A5:A39) -> 35 | C9: Model risk domains scored against the strongest comparator.
A10: Mean current Australian score (0-5) | B10: =ROUND(AVERAGE('Gap Assessment'!H5:H39),2) -> 2.28 | C10: Weighted mean across all domains of the framework as it stands today.
A11: Mean expected score after CPS XXXX | B11: =ROUND(AVERAGE('Gap Assessment'!L5:L39),2) -> 4.41 | C11: Expected position once CPS XXXX and CPG XXXX are in force.
A12: Critical priority gaps | B12: =COUNTIF('Gap Assessment'!K5:K39,"Critical") -> 4 | C12: Gaps that could permit material unmanaged model risk.
A13: High priority gaps | B13: =COUNTIF('Gap Assessment'!K5:K39,"High") -> 17 | C13: Significant divergence from the strongest comparator.
A14: Red-team corrections recorded | B14: =COUNTA('Red Team Audit'!A5:A200) -> 66 | C14: Challenges and corrections preserved with evidence.
A15: High-severity red-team items | B15: =COUNTIF('Red Team Audit'!G5:G200,"High") -> 39 | C15: Corrections of greatest legal or factual significance.
A16: Official sources registered | B16: =COUNTA('Source Register'!A5:A200) -> 50 | C16: Sources with an official URL and a recorded check result.
A17: Sources verified from primary text | B17: =COUNTIF('Source Register'!I5:I200,"Verified — primary source") -> 43 | C17: Confirmed by fetching the issuing authority's own document.
A18: Sources not independently confirmed | B18: =COUNTIF('Source Register'!I5:I200,"Unverified — not independently confirmed") -> 0 | C18: Not relied upon for any statement of requirement.
A20: Principal conclusions
A21: 1 | B21: Australia has strong model requirements for regulatory capital models and a strong actuarial control cycle, and very little else. Outside those regimes a model driving material decisions may never be independently validated.
A22: 2 | B22: The largest gaps are conceptual rather than technical: no cross-industry definition of a model, no inventory obligation, no concept of effective challenge, and no requirement to consider model risk in aggregate.
A23: 3 | B23: Model misuse — applying a sound model outside its approved purpose — is one of the two recognised sources of model risk and is almost entirely unaddressed in the current framework.
A24: 4 | B24: The US interagency guidance remains the source of most of the discipline's architecture, but it is supervisory guidance, not law, and should be cited as such.
A25: 5 | B25: Bringing AI models within the model risk framework, with an express boundary rule against the separate AI instrument, avoids the risk of a system being governed as one and not the other.
A26: 6 | B26: Notification should cross-reference the existing CPS 230 and CPS 234 architecture. A model-specific deadline was considered and rejected as conflicting.

Sheet Scoring Methodology
A1: Scoring methodology
A2: POLICY DEVELOPMENT DRAFT — NOT IN FORCE | Weights and thresholds below are inputs. Change them and the Gap Assessment recalculates.
A4: Element | B4: Definition
A5: What is scored | B5: The CURRENT Australian prudential framework, as it stands before CPS 240, in each model risk domain. Not entity maturity, and not a ranking of the comparator authorities against one another.
A6: Against what | B6: The strongest comparator practice in that domain, identified by authority. Where no comparator addresses a domain at all — superannuation models — the benchmark is recorded as absent and the domain is assessed against the standard's own cross-industry objective instead.
A7: Scale | B7: 0 to 5 on each of four dimensions. The domain score is the unweighted mean of the four dimensions, so no single dimension can carry a domain.
A8: Why four dimensions | B8: A domain can be addressed but vaguely, or precisely but only in guidance. Splitting coverage from specificity from enforceability prevents a general obligation in a binding standard from scoring as though it were a specific one.
A10: The four dimensions
A11: Coverage | B11: Is the domain addressed at all in the framework?
A12: Specificity | B12: Is the expectation precise enough to be evidenced and supervised?
A13: Enforceability | B13: For Australia: binding instrument, guidance, or nothing? Comparator benchmarks are not scored on this dimension, since most of the strongest model risk expectations internationally sit in supervisory guidance rather than law.
A14: Alignment | B14: Does it match the strongest comparator practice?
A16: The 0–5 rubric
A17: Score | B17: Meaning
A18: 5 — Leading practice | B18: Addressed comprehensively and specifically enough that compliance can be evidenced and supervised. Matches or exceeds the strongest comparator. Scored on the quality and specificity of the expectation, irrespective of the instrument type carrying it — enforceability is scored separately.
A19: 4 — Strong | B19: Addressed with clear expectations. Minor gaps in specificity or in coverage of edge cases relative to the strongest comparator.
A20: 3 — Adequate | B20: Addressed, but at a level of generality that leaves material discretion, or in a way that would be difficult to supervise consistently.
A21: 2 — Partial | B21: Addressed indirectly or by implication, through a general obligation not specific to model risk. Compliance would be difficult to evidence or to supervise consistently.
A22: 1 — Incidental | B22: Touched on only for a narrow class of models or entities, or mentioned without expectation.
A23: 0 — Absent | B23: Not addressed in the framework at all.
A25: Derived measures
A26: Domain score | B26: Mean of the four dimension scores for Australia. Column H of Gap Assessment.
A27: Benchmark | B27: The strongest comparator score in that domain, with the authority named. Column I of Gap Assessment.
A28: Gap | B28: MAX(0, Benchmark − Domain score). Negative gaps are floored at zero: where Australia already matches or exceeds the benchmark there is nothing to close.
A29: Weighted gap | B29: Gap × domain weight. This is what drives the priority band.
A30: Expected score after CPS XXXX | B30: Assessed position once the draft standard and guide are in force, on the same 0–5 scale. The difference from the current score is the value the instrument is expected to add.
A32: Priority band thresholds — editable
A33: Band | B33: Weighted gap at or above | C33: Meaning
A34: Critical | B34: 4.5 | C34: Framework gap of a kind that could permit material unmanaged model risk. Address before or at consultation.
A35: High | B35: 3 | C35: Significant divergence from the strongest comparator with a clear prudential rationale for closing it.
A36: Medium | B36: 1.5 | C36: Meaningful but not urgent. Suitable for the practice guide or for supervisory attention rather than a new obligation.
A37: Low | B37: 0 | C37: Broadly comparable to international practice. No action proposed.
A39: Domain weights — editable
A40: Domain | B40: Weight | C40: Why this weight
A41: Definition of a model and of model risk | B41: 1.5 | C41: Direct effect on capital, provisions, reported figures or member outcomes.
A42: Enterprise-wide scope and retained accountability | B42: 1.25 | C42: Material to the integrity of the framework as a whole.
A43: Model inventory | B43: 1.25 | C43: Material to the integrity of the framework as a whole.
A44: Model risk tiering and proportionality | B44: 1.25 | C44: Material to the integrity of the framework as a whole.
A45: Board oversight of model risk | B45: 1.5 | C45: Direct effect on capital, provisions, reported figures or member outcomes.
A46: Senior accountability for the framework | B46: 1.25 | C46: Material to the integrity of the framework as a whole.
A47: MRM framework, policies and capability | B47: 1.25 | C47: Material to the integrity of the framework as a whole.
A48: Model risk appetite | B48: 1 | C48: Important but lower direct prudential consequence.
A49: Development and conceptual soundness | B49: 1.25 | C49: Material to the integrity of the framework as a whole.
A50: Data quality, provenance and appropriateness | B50: 1.25 | C50: Material to the integrity of the framework as a whole.
A51: Documentation and reproducibility | B51: 1 | C51: Important but lower direct prudential consequence.
A52: Pre-implementation testing | B52: 1.25 | C52: Material to the integrity of the framework as a whole.
... A75: Supervisory engagement and notification | B75: 1 | C75: Important but lower direct prudential consequence.
A77: Worked example
A78: 'Definition of a model and of model risk' scores 1, 1, 2 and 1 on coverage, specificity, enforceability and alignment, giving a domain score of 1.25. The strongest comparator is PRA / OSFI at 5. The gap is 5 − 1.25 = 3.75. The domain weight is 1.5, so the weighted gap is 5.62, which falls in the Critical band. After CPS XXXX the expected score is 4.5.
A80: Limitations of this scoring
A81: • Scores are informed judgements against published instruments, not measurements. Two assessors could reasonably differ by a point on any single dimension.
A82: • The benchmark is the strongest comparator practice, which sets a demanding bar. A score of 3 is not a failing framework; it is a framework materially less specific than the leading one.
A83: • Legal status is scored as it stands in the home jurisdiction. It does not imply that any overseas instrument has effect in Australia.
A84: • The expected post-CPS XXXX score assumes the draft is issued substantially as drafted and is implemented as intended. It is a design expectation, not an outcome.

Sheet Gap Assessment
A1: Gap assessment — current Australian framework against strongest comparator
A2: POLICY DEVELOPMENT DRAFT — NOT IN FORCE | Scores 0–5 per the Scoring Methodology sheet. Every score cell carries a comment giving the reasoning.
A4: Domain | B4: Coverage | C4: Specificity | D4: Enforceability | E4: Alignment | F4: Weight | G4: Benchmark authority | H4: AU score now | I4: Benchmark | J4: Weighted gap | K4: Priority | L4: Expected after CPS XXXX | M4: Uplift | N4: CPS XXXX requirements | O4: Source IDs
A5: Definition of a model and of model risk | B5: 1 | C5: 1 | D5: 2 | E5: 1 | F5: ='Scoring Methodology'!$B$41 -> 1.5 | G5: PRA / OSFI | H5: =ROUND(AVERAGE(B5:E5),2) -> 1.25 | I5: 5 | J5: =ROUND(MAX(0,I5-H5)*F5,2) -> 5.63 | K5: =IF(J5>='Scoring Methodology'!$B$34,"Critical",IF(J5>='Scoring Methodology'!$B$35,"High",IF(J5>='Scoring Methodology'!$B$36,"Medium","Low"))) -> Critical | L5: 4.5 | M5: =ROUND(L5-H5,2) -> 3.25 | N5: M02, M03 | O5: US-MRM-2026, PRA-SS1-23, OSFI-E23
A6: Enterprise-wide scope and retained accountability | B6: 2 | C6: 2 | D6: 3 | E6: 2 | F6: ='Scoring Methodology'!$B$42 -> 1.25 | G6: OSFI | H6: =ROUND(AVERAGE(B6:E6),2) -> 2.25 | I6: 5 | J6: =ROUND(MAX(0,I6-H6)*F6,2) -> 3.44 | K6: =IF(J6>='Scoring Methodology'!$B$34,"Critical",IF(J6>='Scoring Methodology'!$B$35,"High",IF(J6>='Scoring Methodology'!$B$36,"Medium","Low"))) -> High | L6: 4.5 | M6: =ROUND(L6-H6,2) -> 2.25 | N6: M01 | O6: OSFI-E23, US-MRM-2026, APRA-CPS220
A7: Model inventory | B7: 1 | C7: 1 | D7: 2 | E7: 1 | F7: ='Scoring Methodology'!$B$43 -> 1.25 | G7: PRA | H7: =ROUND(AVERAGE(B7:E7),2) -> 1.25 | I7: 5 | J7: =ROUND(MAX(0,I7-H7)*F7,2) -> 4.69 | K7: =IF(J7>='Scoring Methodology'!$B$34,"Critical",IF(J7>='Scoring Methodology'!$B$35,"High",IF(J7>='Scoring Methodology'!$B$36,"Medium","Low"))) -> Critical | L7: 4.5 | M7: =ROUND(L7-H7,2) -> 3.25 | N7: M14 | O7: PRA-SS1-23, OSFI-E23, US-MRM-2026
A8: Model risk tiering and proportionality | B8: 2 | C8: 1 | D8: 3 | E8: 2 | F8: ='Scoring Methodology'!$B$44 -> 1.25 | G8: PRA | H8: =ROUND(AVERAGE(B8:E8),2) -> 2 | I8: 5 | J8: =ROUND(MAX(0,I8-H8)*F8,2) -> 3.75 | K8: =IF(J8>='Scoring Methodology'!$B$34,"Critical",IF(J8>='Scoring Methodology'!$B$35,"High",IF(J8>='Scoring Methodology'!$B$36,"Medium","Low"))) -> High | L8: 4.5 | M8: =ROUND(L8-H8,2) -> 2.5 | N8: M04, M05, M15, M16 | O8: PRA-SS1-23, OSFI-E23
A9: Board oversight of model risk | B9: 2 | C9: 2 | D9: 4 | E9: 2 | F9: ='Scoring Methodology'!$B$45 -> 1.5 | G9: PRA | H9: =ROUND(AVERAGE(B9:E9),2) -> 2.5 | I9: 5 | J9: =ROUND(MAX(0,I9-H9)*F9,2) -> 3.75 | K9: =IF(J9>='Scoring Methodology'!$B$34,"Critical",IF(J9>='Scoring Methodology'!$B$35,"High",IF(J9>='Scoring Methodology'!$B$36,"Medium","Low"))) -> High | L9: 4.5 | M9: =ROUND(L9-H9,2) -> 2 | N9: M06, M13 | O9: PRA-SS1-23, OSFI-E23, APRA-CPS220
A10: Senior accountability for the framework | B10: 2 | C10: 2 | D10: 4 | E10: 2 | F10: ='Scoring Methodology'!$B$46 -> 1.25 | G10: PRA | H10: =ROUND(AVERAGE(B10:E10),2) -> 2.5 | I10: 5 | J10: =ROUND(MAX(0,I10-H10)*F10,2) -> 3.13 | K10: =IF(J10>='Scoring Methodology'!$B$34,"Critical",IF(J10>='Scoring Methodology'!$B$35,"High",IF(J10>='Scoring Methodology'!$B$36,"Medium","Low"))) -> High | L10: 4.5 | M10: =ROUND(L10-H10,2) -> 2 | N10: M07, M08 | O10: PRA-SS1-23, OSFI-E23
A11: MRM framework, policies and capability | B11: 2 | C11: 1 | D11: 3 | E11: 2 | F11: ='Scoring Methodology'!$B$47 -> 1.25 | G11: PRA / OSFI | H11: =ROUND(AVERAGE(B11:E11),2) -> 2 | I11: 5 | J11: =ROUND(MAX(0,I11-H11)*F11,2) -> 3.75 | K11: =IF(J11>='Scoring Methodology'!$B$34,"Critical",IF(J11>='Scoring Methodology'!$B$35,"High",IF(J11>='Scoring Methodology'!$B$36,"Medium","Low"))) -> High | L11: 4.5 | M11: =ROUND(L11-H11,2) -> 2.5 | N11: M09, M10, M12 | O11: PRA-SS1-23, OSFI-E23, APRA-CPS220
A12: Model risk appetite | B12: 2 | C12: 1 | D12: 3 | E12: 2 | F12: ='Scoring Methodology'!$B$48 -> 1 | G12: PRA | H12: =ROUND(AVERAGE(B12:E12),2) -> 2 | I12: 4 | J12: =ROUND(MAX(0,I12-H12)*F12,2) -> 2 | K12: =IF(J12>='Scoring Methodology'!$B$34,"Critical",IF(J12>='Scoring Methodology'!$B$35,"High",IF(J12>='Scoring Methodology'!$B$36,"Medium","Low"))) -> Medium | L12: 4 | M12: =ROUND(L12-H12,2) -> 2 | N12: M11 | O12: PRA-SS1-23, OSFI-E23, APRA-CPS220
A13: Development and conceptual soundness | B13: 2 | C13: 2 | D13: 4 | E13: 2 | F13: ='Scoring Methodology'!$B$49 -> 1.25 | G13: US interagency (OCC/FRB/FDIC) | H13: =ROUND(AVERAGE(B13:E13),2) -> 2.5 | I13: 5 | J13: =ROUND(MAX(0,I13-H13)*F13,2) -> 3.13 | K13: =IF(J13>='Scoring Methodology'!$B$34,"Critical",IF(J13>='Scoring Methodology'!$B$35,"High",IF(J13>='Scoring Methodology'!$B$36,"Medium","Low"))) -> High | L13: 4.5 | M13: =ROUND(L13-H13,2) -> 2 | N13: M17 | O13: US-MRM-2026, PRA-SS1-23, ECB-GIM
A14: Data quality, provenance and appropriateness | B14: 3 | C14: 2 | D14: 3 | E14: 3 | F14: ='Scoring Methodology'!$B$50 -> 1.25 | G14: BCBS / ECB | H14: =ROUND(AVERAGE(B14:E14),2) -> 2.75 | I14: 5 | J14: =ROUND(MAX(0,I14-H14)*F14,2) -> 2.81 | K14: =IF(J14>='Scoring Methodology'!$B$34,"Critical",IF(J14>='Scoring Methodology'!$B$35,"High",IF(J14>='Scoring Methodology'!$B$36,"Medium","Low"))) -> Medium | L14: 4.5 | M14: =ROUND(L14-H14,2) -> 1.75 | N14: M18 | O14: BCBS-239, ECB-RDARR, APRA-CPG235, OSFI-E23
A15: Documentation and reproducibility | B15: 2 | C15: 2 | D15: 3 | E15: 2 | F15: ='Scoring Methodology'!$B$51 -> 1 | G15: ECB / PRA | H15: =ROUND(AVERAGE(B15:E15),2) -> 2.25 | I15: 5 | J15: =ROUND(MAX(0,I15-H15)*F15,2) -> 2.75 | K15: =IF(J15>='Scoring Methodology'!$B$34,"Critical",IF(J15>='Scoring Methodology'!$B$35,"High",IF(J15>='Scoring Methodology'!$B$36,"Medium","Low"))) -> Medium | L15: 4.5 | M15: =ROUND(L15-H15,2) -> 2.25 | N15: M19 | O15: US-MRM-2026, PRA-SS1-23, ECB-GIM
A16: Pre-implementation testing | B16: 2 | C16: 1 | D16: 3 | E16: 2 | F16: ='Scoring Methodology'!$B$52 -> 1.25 | G16: PRA / ECB | H16: =ROUND(AVERAGE(B16:E16),2) -> 2 | I16: 5 | J16: =ROUND(MAX(0,I16-H16)*F16,2) -> 3.75 | K16: =IF(J16>='Scoring Methodology'!$B$34,"Critical",IF(J16>='Scoring Methodology'!$B$35,"High",IF(J16>='Scoring Methodology'!$B$36,"Medium","Low"))) -> High | L16: 4.5 | M16: =ROUND(L16-H16,2) -> 2.5 | N16: M20 | O16: US-MRM-2026, PRA-SS1-23, OSFI-E23
A17: Independent validation | B17: 2 | C17: 2 | D17: 4 | E17: 2 | F17: ='Scoring Methodology'!$B$53 -> 1.5 | G17: PRA | H17: =ROUND(AVERAGE(B17:E17),2) -> 2.5 | I17: 5 | J17: =ROUND(MAX(0,I17-H17)*F17,2) -> 3.75 | K17: =IF(J17>='Scoring Methodology'!$B$34,"Critical",IF(J17>='Scoring Methodology'!$B$35,"High",IF(J17>='Scoring Methodology'!$B$36,"Medium","Low"))) -> High | L17: 5 | M17: =ROUND(L17-H17,2) -> 2.5 | N17: M21, M22, M25 | O17: PRA-SS1-23, US-MRM-2026, OSFI-E23, ECB-GIM
A18: Effective challenge | B18: 1 | C18: 1 | D18: 2 | E18: 1 | F18: ='Scoring Methodology'!$B$54 -> 1.5 | G18: US interagency (OCC/FRB/FDIC) | H18: =ROUND(AVERAGE(B18:E18),2) -> 1.25 | I18: 5 | J18: =ROUND(MAX(0,I18-H18)*F18,2) -> 5.63 | K18: =IF(J18>='Scoring Methodology'!$B$34,"Critical",IF(J18>='Scoring Methodology'!$B$35,"High",IF(J18>='Scoring Methodology'!$B$36,"Medium","Low"))) -> Critical | L18: 4.5 | M18: =ROUND(L18-H18,2) -> 3.25 | N18: M23 | O18: US-MRM-2026, PRA-SS1-23
A19: Approval and conditions of use | B19: 2 | C19: 2 | D19: 4 | E19: 2 | F19: ='Scoring Methodology'!$B$55 -> 1 | G19: ECB | H19: =ROUND(AVERAGE(B19:E19),2) -> 2.5 | I19: 5 | J19: =ROUND(MAX(0,I19-H19)*F19,2) -> 2.5 | K19: =IF(J19>='Scoring Methodology'!$B$34,"Critical",IF(J19>='Scoring Methodology'!$B$35,"High",IF(J19>='Scoring Methodology'!$B$36,"Medium","Low"))) -> Medium | L19: 4.5 | M19: =ROUND(L19-H19,2) -> 2 | N19: M24 | O19: ECB-GIM, OSFI-E23, US-MRM-2026
A20: Implementation controls | B20: 1 | C20: 1 | D20: 3 | E20: 1 | F20: ='Scoring Methodology'!$B$56 -> 1 | G20: ECB | H20: =ROUND(AVERAGE(B20:E20),2) -> 1.5 | I20: 5 | J20: =ROUND(MAX(0,I20-H20)*F20,2) -> 3.5 | K20: =IF(J20>='Scoring Methodology'!$B$34,"Critical",IF(J20>='Scoring Methodology'!$B$35,"High",IF(J20>='Scoring Methodology'!$B$36,"Medium","Low"))) -> High | L20: 4 | M20: =ROUND(L20-H20,2) -> 2.5 | N20: M25 | O20: ECB-GIM, US-MRM-2026, OSFI-E23
A21: Change management and re-approval | B21: 2 | C21: 2 | D21: 4 | E21: 2 | F21: ='Scoring Methodology'!$B$57 -> 1.25 | G21: ECB | H21: =ROUND(AVERAGE(B21:E21),2) -> 2.5 | I21: 5 | J21: =ROUND(MAX(0,I21-H21)*F21,2) -> 3.13 | K21: =IF(J21>='Scoring Methodology'!$B$34,"Critical",IF(J21>='Scoring Methodology'!$B$35,"High",IF(J21>='Scoring Methodology'!$B$36,"Medium","Low"))) -> High | L21: 4.5 | M21: =ROUND(L21-H21,2) -> 2 | N21: M26 | O21: ECB-GIM, OSFI-E23, PRA-SS1-23
A22: Model use and misuse | B22: 1 | C22: 1 | D22: 3 | E22: 1 | F22: ='Scoring Methodology'!$B$58 -> 1.25 | G22: US interagency / ECB | H22: =ROUND(AVERAGE(B22:E22),2) -> 1.5 | I22: 5 | J22: =ROUND(MAX(0,I22-H22)*F22,2) -> 4.38 | K22: =IF(J22>='Scoring Methodology'!$B$34,"Critical",IF(J22>='Scoring Methodology'!$B$35,"High",IF(J22>='Scoring Methodology'!$B$36,"Medium","Low"))) -> High | L22: 4.5 | M22: =ROUND(L22-H22,2) -> 3 | N22: M27 | O22: US-MRM-2026, ECB-GIM, PRA-SS1-23
A23: Overlays, adjustments and expert judgement | B23: 2 | C23: 1 | D23: 3 | E23: 2 | F23: ='Scoring Methodology'!$B$59 -> 1.25 | G23: PRA | H23: =ROUND(AVERAGE(B23:E23),2) -> 2 | I23: 5 | J23: =ROUND(MAX(0,I23-H23)*F23,2) -> 3.75 | K23: =IF(J23>='Scoring Methodology'!$B$34,"Critical",IF(J23>='Scoring Methodology'!$B$35,"High",IF(J23>='Scoring Methodology'!$B$36,"Medium","Low"))) -> High | L23: 4.5 | M23: =ROUND(L23-H23,2) -> 2.5 | N23: M28 | O23: PRA-SS1-23, ECB-GIM
A24: Ongoing monitoring and drift | B24: 2 | C24: 2 | D24: 3 | E24: 2 | F24: ='Scoring Methodology'!$B$60 -> 1.25 | G24: US interagency / OSFI | H24: =ROUND(AVERAGE(B24:E24),2) -> 2.25 | I24: 5 | J24: =ROUND(MAX(0,I24-H24)*F24,2) -> 3.44 | K24: =IF(J24>='Scoring Methodology'!$B$34,"Critical",IF(J24>='Scoring Methodology'!$B$35,"High",IF(J24>='Scoring Methodology'!$B$36,"Medium","Low"))) -> High | L24: 4.5 | M24: =ROUND(L24-H24,2) -> 2.25 | N24: M29 | O24: US-MRM-2026, OSFI-E23, PRA-SS1-23
A25: Limitations, mitigants and remediation | B25: 2 | C25: 1 | D25: 3 | E25: 2 | F25: ='Scoring Methodology'!$B$61 -> 1 | G25: PRA | H25: =ROUND(AVERAGE(B25:E25),2) -> 2 | I25: 5 | J25: =ROUND(MAX(0,I25-H25)*F25,2) -> 3 | K25: =IF(J25>='Scoring Methodology'!$B$34,"Critical",IF(J25>='Scoring Methodology'!$B$35,"High",IF(J25>='Scoring Methodology'!$B$36,"Medium","Low"))) -> High | L25: 4.5 | M25: =ROUND(L25-H25,2) -> 2.5 | N25: M30 | O25: PRA-SS1-23, US-MRM-2026
A26: Decommissioning and retirement | B26: 1 | C26: 1 | D26: 2 | E26: 1 | F26: ='Scoring Methodology'!$B$62 -> 0.75 | G26: OSFI | H26: =ROUND(AVERAGE(B26:E26),2) -> 1.25 | I26: 4 | J26: =ROUND(MAX(0,I26-H26)*F26,2) -> 2.06 | K26: =IF(J26>='Scoring Methodology'!$B$34,"Critical",IF(J26>='Scoring Methodology'!$B$35,"High",IF(J26>='Scoring Methodology'!$B$36,"Medium","Low"))) -> Medium | L26: 4 | M26: =ROUND(L26-H26,2) -> 2.75 | N26: M31 | O26: OSFI-E23, APRA-CPS230
A27: Third-party and vendor models | B27: 2 | C27: 2 | D27: 4 | E27: 2 | F27: ='Scoring Methodology'!$B$63 -> 1.25 | G27: US interagency / PRA | H27: =ROUND(AVERAGE(B27:E27),2) -> 2.5 | I27: 5 | J27: =ROUND(MAX(0,I27-H27)*F27,2) -> 3.13 | K27: =IF(J27>='Scoring Methodology'!$B$34,"Critical",IF(J27>='Scoring Methodology'!$B$35,"High",IF(J27>='Scoring Methodology'!$B$36,"Medium","Low"))) -> High | L27: 4.5 | M27: =ROUND(L27-H27,2) -> 2 | N27: M32, M33 | O27: US-MRM-2026, PRA-SS1-23, BCBS-TPRM, APRA-CPS230
A28: Concentration and substitutability | B28: 2 | C28: 1 | D28: 3 | E28: 2 | F28: ='Scoring Methodology'!$B$64 -> 1 | G28: FSB / BCBS | H28: =ROUND(AVERAGE(B28:E28),2) -> 2 | I28: 4 | J28: =ROUND(MAX(0,I28-H28)*F28,2) -> 2 | K28: =IF(J28>='Scoring Methodology'!$B$34,"Critical",IF(J28>='Scoring Methodology'!$B$35,"High",IF(J28>='Scoring Methodology'!$B$36,"Medium","Low"))) -> Medium | L28: 4 | M28: =ROUND(L28-H28,2) -> 2 | N28: M33 | O28: FSB-AI-2024, BCBS-TPRM, APRA-CPS230
A29: AI and machine learning models | B29: 2 | C29: 2 | D29: 3 | E29: 2 | F29: ='Scoring Methodology'!$B$65 -> 1.25 | G29: OSFI | H29: =ROUND(AVERAGE(B29:E29),2) -> 2.25 | I29: 5 | J29: =ROUND(MAX(0,I29-H29)*F29,2) -> 3.44 | K29: =IF(J29>='Scoring Methodology'!$B$34,"Critical",IF(J29>='Scoring Methodology'!$B$35,"High",IF(J29>='Scoring Methodology'!$B$36,"Medium","Low"))) -> High | L29: 4.5 | M29: =ROUND(L29-H29,2) -> 2.25 | N29: M34, M35 | O29: OSFI-E23, MAS-AIMRM-2024, BCBS-DIGI, FSB-AI-2024
A30: Regulatory capital and internal models | B30: 4 | C30: 4 | D30: 5 | E30: 4 | F30: ='Scoring Methodology'!$B$66 -> 1.5 | G30: ECB | H30: =ROUND(AVERAGE(B30:E30),2) -> 4.25 | I30: 5 | J30: =ROUND(MAX(0,I30-H30)*F30,2) -> 1.13 | K30: =IF(J30>='Scoring Methodology'!$B$34,"Critical",IF(J30>='Scoring Methodology'!$B$35,"High",IF(J30>='Scoring Methodology'!$B$36,"Medium","Low"))) -> Low | L30: 4.75 | M30: =ROUND(L30-H30,2) -> 0.5 | N30: M36 | O30: APRA-APS113, ECB-GIM, ECB-CRR, PRA-SS1-23
A31: Valuation and financial reporting models | B31: 2 | C31: 2 | D31: 3 | E31: 2 | F31: ='Scoring Methodology'!$B$67 -> 1.25 | G31: BCBS | H31: =ROUND(AVERAGE(B31:E31),2) -> 2.25 | I31: 4 | J31: =ROUND(MAX(0,I31-H31)*F31,2) -> 2.19 | K31: =IF(J31>='Scoring Methodology'!$B$34,"Critical",IF(J31>='Scoring Methodology'!$B$35,"High",IF(J31>='Scoring Methodology'!$B$36,"Medium","Low"))) -> Medium | L31: 4 | M31: =ROUND(L31-H31,2) -> 1.75 | N31: M37 | O31: BCBS-FVP, ECB-GIM
A32: Expected credit loss and provisioning models | B32: 4 | C32: 4 | D32: 5 | E32: 4 | F32: ='Scoring Methodology'!$B$68 -> 1.5 | G32: BCBS | H32: =ROUND(AVERAGE(B32:E32),2) -> 4.25 | I32: 5 | J32: =ROUND(MAX(0,I32-H32)*F32,2) -> 1.13 | K32: =IF(J32>='Scoring Methodology'!$B$34,"Critical",IF(J32>='Scoring Methodology'!$B$35,"High",IF(J32>='Scoring Methodology'!$B$36,"Medium","Low"))) -> Low | L32: 4.75 | M32: =ROUND(L32-H32,2) -> 0.5 | N32: M38 | O32: APRA-APS220, APRA-APG220, BCBS-ECL-2015, APRA-PROV-2023, AASB-9, APRA-APS310
A33: Actuarial and insurance models | B33: 3 | C33: 3 | D33: 4 | E33: 3 | F33: ='Scoring Methodology'!$B$69 -> 1.25 | G33: OSFI | H33: =ROUND(AVERAGE(B33:E33),2) -> 3.25 | I33: 4 | J33: =ROUND(MAX(0,I33-H33)*F33,2) -> 0.94 | K33: =IF(J33>='Scoring Methodology'!$B$34,"Critical",IF(J33>='Scoring Methodology'!$B$35,"High",IF(J33>='Scoring Methodology'!$B$36,"Medium","Low"))) -> Low | L33: 4.5 | M33: =ROUND(L33-H33,2) -> 1.25 | N33: M39 | O33: APRA-CPS320, OSFI-E23
A34: Superannuation models | B34: 1 | C34: 1 | D34: 3 | E34: 1 | F34: ='Scoring Methodology'!$B$70 -> 1.25 | G34: No comparator — assessed against the standard's own cross-industry objective | H34: =ROUND(AVERAGE(B34:E34),2) -> 1.5 | I34: 5 | J34: =ROUND(MAX(0,I34-H34)*F34,2) -> 4.38 | K34: =IF(J34>='Scoring Methodology'!$B$34,"Critical",IF(J34>='Scoring Methodology'!$B$35,"High",IF(J34>='Scoring Methodology'!$B$36,"Medium","Low"))) -> High | L34: 4 | M34: =ROUND(L34-H34,2) -> 2.5 | N34: M40 | O34: APRA-SPS530, APRA-SPS515
A35: Stress testing and scenario models | B35: 3 | C35: 2 | D35: 4 | E35: 3 | F35: ='Scoring Methodology'!$B$71 -> 1 | G35: PRA / BCBS | H35: =ROUND(AVERAGE(B35:E35),2) -> 3 | I35: 5 | J35: =ROUND(MAX(0,I35-H35)*F35,2) -> 2 | K35: =IF(J35>='Scoring Methodology'!$B$34,"Critical",IF(J35>='Scoring Methodology'!$B$35,"High",IF(J35>='Scoring Methodology'!$B$36,"Medium","Low"))) -> Medium | L35: 4.5 | M35: =ROUND(L35-H35,2) -> 1.5 | N35: M41 | O35: BCBS-STRESS, PRA-SS3-18, APRA-CPS220
A36: Aggregate model risk and capital | B36: 1 | C36: 1 | D36: 2 | E36: 1 | F36: ='Scoring Methodology'!$B$72 -> 1.25 | G36: PRA | H36: =ROUND(AVERAGE(B36:E36),2) -> 1.25 | I36: 5 | J36: =ROUND(MAX(0,I36-H36)*F36,2) -> 4.69 | K36: =IF(J36>='Scoring Methodology'!$B$34,"Critical",IF(J36>='Scoring Methodology'!$B$35,"High",IF(J36>='Scoring Methodology'!$B$36,"Medium","Low"))) -> Critical | L36: 4 | M36: =ROUND(L36-H36,2) -> 2.75 | N36: M42 | O36: PRA-SS1-23, ECB-GIM, US-MRM-2026, APRA-SPS114
A37: Records and reconstructability | B37: 2 | C37: 2 | D37: 4 | E37: 2 | F37: ='Scoring Methodology'!$B$73 -> 1 | G37: ECB | H37: =ROUND(AVERAGE(B37:E37),2) -> 2.5 | I37: 4 | J37: =ROUND(MAX(0,I37-H37)*F37,2) -> 1.5 | K37: =IF(J37>='Scoring Methodology'!$B$34,"Critical",IF(J37>='Scoring Methodology'!$B$35,"High",IF(J37>='Scoring Methodology'!$B$36,"Medium","Low"))) -> Medium | L37: 4 | M37: =ROUND(L37-H37,2) -> 1.5 | N37: M43 | O37: ECB-GIM, US-MRM-2026, APRA-CPS220
A38: Independent assurance and internal audit | B38: 3 | C38: 2 | D38: 4 | E38: 3 | F38: ='Scoring Methodology'!$B$74 -> 1.25 | G38: PRA | H38: =ROUND(AVERAGE(B38:E38),2) -> 3 | I38: 5 | J38: =ROUND(MAX(0,I38-H38)*F38,2) -> 2.5 | K38: =IF(J38>='Scoring Methodology'!$B$34,"Critical",IF(J38>='Scoring Methodology'!$B$35,"High",IF(J38>='Scoring Methodology'!$B$36,"Medium","Low"))) -> Medium | L38: 4.5 | M38: =ROUND(L38-H38,2) -> 1.5 | N38: M44 | O38: PRA-SS1-23, US-MRM-2026, ECB-GIM, APRA-CPS220
A39: Supervisory engagement and notification | B39: 3 | C39: 3 | D39: 4 | E39: 3 | F39: ='Scoring Methodology'!$B$75 -> 1 | G39: OSFI | H39: =ROUND(AVERAGE(B39:E39),2) -> 3.25 | I39: 4 | J39: =ROUND(MAX(0,I39-H39)*F39,2) -> 0.75 | K39: =IF(J39>='Scoring Methodology'!$B$34,"Critical",IF(J39>='Scoring Methodology'!$B$35,"High",IF(J39>='Scoring Methodology'!$B$36,"Medium","Low"))) -> Low | L39: 4.25 | M39: =ROUND(L39-H39,2) -> 1 | N39: M45 | O39: APRA-CPS230, APRA-CPS234, OSFI-E23
A41: Totals | H41: =ROUND(AVERAGE(H5:H39),2) -> 2.28 | J41: =ROUND(SUM(J5:J39),2) -> 107.5 | L41: =ROUND(AVERAGE(L5:L39),2) -> 4.41 | M41: =ROUND(L41-H41,2) -> 2.13 | N41: Mean AU score, total weighted gap, mean expected score, mean uplift.

Sheet Areas for Improvement
A1: Areas for improvement
A2: POLICY DEVELOPMENT DRAFT — NOT IN FORCE | Ordered by weighted gap. Priority and weighted gap are linked to the Gap Assessment sheet, so re-weighting there re-ranks nothing here automatically — re-sort after changing weights.
A4: Rank | B4: Domain | C4: Priority | D4: Weighted gap | E4: Observed gap | F4: Recommended action | G4: CPS XXXX requirements | H4: Indicative owner | I4: Status
A5: 1 | B5: Definition of a model and of model risk | C5: ='Gap Assessment'!K5 -> Critical | D5: ='Gap Assessment'!J5 -> 5.63 | E5: No APRA instrument defines a model or model risk on a cross-industry basis. Model requirements exist only inside the capital and actuarial standards and apply only to the models those standards cover. | F5: Adopt a broad function-based definition of a model and of model risk on a cross-industry basis, with an express obligation to identify and control quantitative tools falling outside it. Do not follow the April 2026 United States narrowing, which would exclude actuarial and unit pricing calculations. | G5: M02, M03 | H5: Policy | I5: Open — policy development
A6: 2 | B6: Effective challenge | C6: ='Gap Assessment'!K18 -> Critical | D6: ='Gap Assessment'!J18 -> 5.63 | E6: The concept is absent from the Australian framework. Validation can exist on paper without the competence, standing or incentives that make it effective, and nothing currently requires an entity to test whether challenge works. | F6: Require effective challenge expressly, and expect entities to assess whether it is operating through finding closure routes and severity migration. | G6: M23 | H6: Policy + Supervision | I6: Open — policy development
A7: 3 | B7: Model inventory | C7: ='Gap Assessment'!K7 -> Critical | D7: ='Gap Assessment'!J7 -> 4.69 | E7: No cross-industry inventory obligation. Without one, no other model risk obligation can be evidenced as complete, and APRA cannot assess sector-wide reliance. | F7: Require a complete, current, controlled enterprise inventory including embedded, third-party and recently decommissioned models, with minimum fields specified. | G7: M14 | H7: Policy + Supervision | I7: Open — policy development
A8: 4 | B8: Aggregate model risk and capital | C8: ='Gap Assessment'!K36 -> Critical | D8: ='Gap Assessment'!J36 -> 4.69 | E8: Nothing requires an entity to form a view of model risk in aggregate or to consider it in internal capital assessment, so correlated failure across models sharing data, vendors or assumptions is invisible. | F8: Require aggregate assessment and consideration in internal capital assessment, permitting qualitative measures where quantification is not yet feasible. | G8: M42 | H8: Policy + Capital | I8: Open — policy development
A9: 5 | B9: Model use and misuse | C9: ='Gap Assessment'!K22 -> High | D9: ='Gap Assessment'!J22 -> 4.38 | E9: Misuse is one of the two recognised sources of model risk and is entirely unaddressed outside the capital use test. Nothing requires users to be told a model's limitations. | F9: Require use within approved purpose and conditions, and require limitations to be communicated to users rather than merely recorded. | G9: M27 | H9: Policy | I9: Open — policy development
A10: 6 | B10: Superannuation models | C10: ='Gap Assessment'!K34 -> High | D10: ='Gap Assessment'!J34 -> 4.38 | E10: No comparator authority addresses superannuation model risk, so there is no benchmark. Unit pricing and valuation models determine amounts credited to member accounts and errors transfer value between members irreversibly. | F10: Name the RSE model classes expressly. Scored against the cross-industry benchmark rather than a comparator, because none exists. | G10: M40 | H10: Policy + Superannuation | I10: Open — policy development
A11: 7 | B11: Model risk tiering and proportionality | C11: ='Gap Assessment'!K8 -> High | D11: ='Gap Assessment'!J8 -> 3.75 | E11: Proportionality is a general principle across APRA standards but there is no model risk classification taxonomy, so control intensity is not systematically linked to model risk. | F11: Require a documented tiering methodology using quantitative and qualitative factors that demonstrably drives validation, monitoring and approval intensity, with an express de minimis determination at model level that keeps low-consequence models within identification while relieving them of the full lifecycle. | G11: M04, M05, M15, M16 | H11: Policy | I11: Open — policy development
A12: 8 | B12: Board oversight of model risk | C12: ='Gap Assessment'!K9 -> High | D12: ='Gap Assessment'!J9 -> 3.75 | E12: CPS 220 gives the Board responsibility for the risk management framework, but model risk is not identified as a risk requiring Board attention in its own right and no reporting content is specified. | F12: Require Board approval of the model risk framework and appetite, supported by aggregate, decision-useful reporting rather than model counts. | G12: M06, M13 | H12: Policy | I12: Open — policy development
A13: 9 | B13: MRM framework, policies and capability | C13: ='Gap Assessment'!K11 -> High | D13: ='Gap Assessment'!J11 -> 3.75 | E13: There is no requirement to maintain a model risk management framework as such, no documented model risk policy standard, and no requirement for capability and independence sufficient to validate and challenge models. Model governance obligations sit inside instruments written for other purposes. | F13: Require a documented framework integrated with the risk management framework, policies applied consistently across the entity, and capability and independence sufficient to develop, use, validate, challenge and assure models. | G13: M09, M10, M12 | H13: Policy | I13: Open — policy development
A14: 10 | B14: Pre-implementation testing | C14: ='Gap Assessment'!K16 -> High | D14: ='Gap Assessment'!J16 -> 3.75 | E14: No general bar on using an untested model. Testing expectations exist only within the capital model approval process. | F14: Establish an explicit gate: a model must not be used for a material purpose until tested and residual limitations accepted. | G14: M20 | H14: Policy | I14: Open — policy development
A15: 11 | B15: Independent validation | C15: ='Gap Assessment'!K17 -> High | D15: ='Gap Assessment'!J17 -> 3.75 | E15: Independent validation is required for IRB models under APS 113 and, in a different form, through the Appointed Actuary. There is no general requirement, so a model driving material decisions outside those regimes may never be independently reviewed. | F15: Require independent validation for material models, structured around conceptual soundness, outcomes analysis and ongoing model monitoring, at an intensity set by tier. | G15: M21, M22, M25 | H15: Policy + Supervision | I15: Open — policy development
A16: 12 | B16: Overlays, adjustments and expert judgement | C16: ='Gap Assessment'!K23 -> High | D16: ='Gap Assessment'!J23 -> 3.75 | E16: Post-model adjustments can become the dominant driver of a reported figure without any single approval considering that effect. No Australian instrument governs them generally or requires aggregate reporting. | F16: Require governance of the basis, quantification, approval, duration and removal of overlays, and aggregate reporting of them. | G16: M28 | H16: Policy | I16: Open — policy development
A17: 13 | B17: Implementation controls | C17: ='Gap Assessment'!K20 -> High | D17: ='Gap Assessment'!J20 -> 3.5 | E17: Nothing requires verification that the deployed model reproduces the approved one. This is a recurrent source of failure that methodological validation does not catch. | F17: Require pre-production verification against the approved model and re-verification after material infrastructure or pipeline change. | G17: M25 | H17: Policy + Technology | I17: Open — policy development
A18: 14 | B18: Enterprise-wide scope and retained accountability | C18: ='Gap Assessment'!K6 -> High | D18: ='Gap Assessment'!J6 -> 3.44 | E18: CPS 220 requires a risk management framework covering material risks but does not name model risk, so enterprise-wide coverage depends on each entity's own characterisation. | F18: State enterprise-wide application expressly and confirm that accountability is retained where a model is supplied or operated by another party. | G18: M01 | H18: Policy | I18: Open — policy development
A19: 15 | B19: Ongoing monitoring and drift | C19: ='Gap Assessment'!K24 -> High | D19: ='Gap Assessment'!J24 -> 3.44 | E19: Monitoring expectations are limited to specific model classes. Thresholds are rarely linked to a defined response, so deterioration produces reporting rather than action. | F19: Require monitoring at tier-based frequency with pre-set thresholds linked to investigation, restriction, revalidation or withdrawal. | G19: M29 | H19: Policy + Risk | I19: Open — policy development
A20: 16 | B20: AI and machine learning models | C20: ='Gap Assessment'!K29 -> High | D20: ='Gap Assessment'!J29 -> 3.44 | E20: AI model risk is being addressed through a separate AI workstream, creating a risk that a model built with AI techniques is governed as an AI system but not as a model, or the reverse. | F20: Bring AI models within the model risk framework as a model class, with an explicit boundary rule against the AI risk instrument so nothing falls between. | G20: M34, M35 | H20: Policy | I20: Open — policy development
A21: 17 | B21: Senior accountability for the framework | C21: ='Gap Assessment'!K10 -> High | D21: ='Gap Assessment'!J10 -> 3.13 | E21: No named accountability for model risk as a discipline. Accountability for individual models is implicit in business ownership but framework-level failures have no owner. | F21: Require a named senior executive accountable for the framework, plus a named owner for each model, and settle the interaction with the accountability regime. | G21: M07, M08 | H21: Policy + Legal | I21: Open — policy development
A22: 18 | B22: Development and conceptual soundness | C22: ='Gap Assessment'!K13 -> High | D22: ='Gap Assessment'!J13 -> 3.13 | E22: Development standards exist only for capital models under APS 113 and for actuarial work. Models outside those regimes have no development expectation. | F22: Require documented development standards, conceptual soundness, consideration of alternatives and recording of limitations across all material models. | G22: M17 | H22: Policy | I22: Open — policy development
A23: 19 | B23: Change management and re-approval | C23: ='Gap Assessment'!K21 -> High | D23: ='Gap Assessment'!J21 -> 3.13 | E23: Model change control is prescribed only for capital models. Cumulative change and vendor-initiated change are not addressed anywhere in the framework. | F23: Require materiality assessment of changes individually and cumulatively, and treat provider-initiated change as an entity change event. | G23: M26 | H23: Policy | I23: Open — policy development
A24: 20 | B24: Third-party and vendor models | C24: ='Gap Assessment'!K27 -> High | D24: ='Gap Assessment'!J27 -> 3.13 | E24: CPS 230 governs service providers but not the model risk in a supplied model. Opacity is commonly accepted from vendors at a level that would not be accepted internally. | F24: Apply the full framework to third-party models, require usable information rights without mandating source-code access, and require compensating controls where information is unavailable. | G24: M32, M33 | H24: Policy + Operational Risk | I24: Open — policy development
A25: 21 | B25: Limitations, mitigants and remediation | C25: ='Gap Assessment'!K25 -> High | D25: ='Gap Assessment'!J25 -> 3 | E25: No requirement to record model limitations, apply compensating controls or track remediation to completion. Findings can be closed by explanation without change. | F25: Require recorded limitations, specific compensating controls, tracked remediation and escalation of overdue material findings. | G25: M30 | H25: Policy | I25: Open — policy development
A26: 22 | B26: Data quality, provenance and appropriateness | C26: ='Gap Assessment'!K14 -> Medium | D26: ='Gap Assessment'!J14 -> 2.81 | E26: CPG 235 provides a data governance foundation but is a practice guide, is dated, and does not address model-specific concerns such as proxy data, representativeness or synthetic data. | F26: Require model data to be assessed for appropriateness as well as quality, with lineage to source and documented treatment of proxies and synthetic data. | G26: M18 | H26: Policy + Data | I26: Open — policy development
A27: 23 | B27: Documentation and reproducibility | C27: ='Gap Assessment'!K15 -> Medium | D27: ='Gap Assessment'!J15 -> 2.75 | E27: No cross-industry documentation standard for models. Documentation adequacy is assessed only where a capital or actuarial standard applies. | F27: Adopt the reconstruction test: documentation sufficient for an independent competent person to reproduce material results. | G27: M19 | H27: Policy | I27: Open — policy development
A28: 24 | B28: Approval and conditions of use | C28: ='Gap Assessment'!K19 -> Medium | D28: ='Gap Assessment'!J19 -> 2.5 | E28: Approval requirements exist for capital models only. Elsewhere, models enter use without a recorded approval of version, purpose or conditions. | F28: Require version-specific approval for a defined purpose and conditions, recording limits, thresholds, accepted limitations and review date. | G28: M24 | H28: Policy | I28: Open — policy development
A29: 25 | B29: Independent assurance and internal audit | C29: ='Gap Assessment'!K38 -> Medium | D29: ='Gap Assessment'!J38 -> 2.5 | E29: Internal audit obligations are general. Audit of the model risk framework, and in particular of whether challenge is effective, is not specified and frequently lacks the technical capability to be meaningful. | F29: Require periodic independent assessment of framework design and operating effectiveness, including the effectiveness of validation and challenge. | G29: M44 | H29: Policy + Assurance | I29: Open — policy development
A30: 26 | B30: Valuation and financial reporting models | C30: ='Gap Assessment'!K31 -> Medium | D30: ='Gap Assessment'!J31 -> 2.19 | E30: Valuation model governance and independent price verification are not addressed on a cross-industry basis, despite the output being the reported number itself. | F30: Bring valuation and financial reporting models expressly within scope and require independent price verification as a control distinct from validation. | G30: M37 | H30: Policy | I30: Open — policy development
A31: 27 | B31: Decommissioning and retirement | C31: ='Gap Assessment'!K26 -> Medium | D31: ='Gap Assessment'!J26 -> 2.06 | E31: Retired models whose outputs remain in force — provisions, capital numbers, unit prices, insurance liabilities — are not addressed anywhere. | F31: Require managed decommissioning covering downstream models, outputs still in force, records and data disposition. | G31: M31 | H31: Policy | I31: Open — policy development
A32: 28 | B32: Model risk appetite | C32: ='Gap Assessment'!K12 -> Medium | D32: ='Gap Assessment'!J12 -> 2 | E32: Risk appetite obligations are general. Model risk is rarely expressed in appetite statements in monitorable terms, so it cannot be breached or escalated. | F32: Require an appetite for model risk expressed so that it can be measured, with limits, thresholds and escalation triggers. | G32: M11 | H32: Policy | I32: Open — policy development
A33: 29 | B33: Concentration and substitutability | C33: ='Gap Assessment'!K28 -> Medium | D33: ='Gap Assessment'!J28 -> 2 | E33: Bilateral service provider assessment does not capture correlated reliance on a common external model, data source or platform across the industry. | F33: Require entity-level concentration assessment and support sector-wide monitoring of common model and data dependencies. | G33: M33 | H33: Supervision + Data | I33: Open — policy development
A34: 30 | B34: Stress testing and scenario models | C34: ='Gap Assessment'!K35 -> Medium | D34: ='Gap Assessment'!J35 -> 2 | E34: APRA conducts stress testing but there is no standard governing the models used, whereas the PRA maintains a dedicated supervisory statement on model risk in stress testing. | F34: Bring stress testing, scenario and capital planning models within scope, with explicit treatment of assumption governance and of uncertainty disclosure. | G34: M41 | H34: Policy + Supervision | I34: Open — policy development
A35: 31 | B35: Records and reconstructability | C35: ='Gap Assessment'!K37 -> Medium | D35: ='Gap Assessment'!J37 -> 1.5 | E35: General record-keeping obligations do not specify what must be retained to reconstruct a model's output, approval basis and performance. | F35: Specify reconstructability for material models, with retention aligned to the period over which the decisions informed remain material. | G35: M43 | H35: Policy + Legal | I35: Open — policy development
A36: 32 | B36: Regulatory capital and internal models | C36: ='Gap Assessment'!K30 -> Low | D36: ='Gap Assessment'!J30 -> 1.13 | E36: This is the strongest part of the Australian framework. The residual gap is the absence of a general model risk discipline around the capital model estate, and less developed guidance on model change than the ECB provides. | F36: Preserve the capital standards unchanged and position CPS XXXX to sit alongside them, with the specific capital requirement governing approval, change and conditions of use. | G36: M36 | H36: Policy + Capital | I36: Open — policy development
A37: 33 | B37: Expected credit loss and provisioning models | C37: ='Gap Assessment'!K32 -> Low | D37: ='Gap Assessment'!J32 -> 1.13 | E37: This is a genuine strength. APS 220 transposes BCBS d350 Principle 5 into binding Australian form in near-identical language, requiring ADIs to have sound policies and processes to appropriately validate expected credit loss models, and APG 220 directs ADIs to have regard to the Basel guidance. The residual gap is that the obligation to validate exists without a model risk framework defining what validation consists of, who performs it and what follows a finding — and that APRA's own observations record continuing reliance on sizeable judgement-based adjustments that are not consistently well governed. | F37: Connect the existing APS 220 validation obligation to the model risk framework rather than restating it, govern overlays and scenario assumptions as model risk, and publish the review focus areas so entities know what an APRA-required review under the special purpose engagement provisions of the Audit and Related Matters standards, or under APS 220, would examine. | G37: M38 | H37: Policy + Credit Risk | I37: Open — policy development
A38: 34 | B38: Actuarial and insurance models | C38: ='Gap Assessment'!K33 -> Low | D38: ='Gap Assessment'!J33 -> 0.94 | E38: The Appointed Actuary framework is a genuine strength but was not designed as model risk management. Implementation verification and data quality assessment are not reliably covered. | F38: Require insurers to map which validation elements the actuarial control cycle discharges and which need separate work. | G38: M39 | H38: Policy + Insurance | I38: Open — policy development
A39: 35 | B39: Supervisory engagement and notification | C39: ='Gap Assessment'!K39 -> Low | D39: ='Gap Assessment'!J39 -> 0.75 | E39: Notification architecture is sound but does not identify model failure as a notifiable event, so a material model error may not be reported unless it also constitutes an operational incident. | F39: Cross-reference existing CPS 230 and CPS 234 timeframes rather than create a conflicting deadline, and expect early engagement on material model weakness. | G39: M45 | H39: Policy + Legal | I39: Open — policy development

Sheet Regulatory Crosswalk
A1: Regulatory crosswalk — model risk management
A2: POLICY DEVELOPMENT DRAFT — NOT IN FORCE | Compares substantive content. Legal enforceability differs between authorities and is recorded on the Legal Status Matrix sheet.
A4: Domain | B4: APRA (current) | C4: OCC / Federal Reserve | D4: PRA | E4: OSFI | F4: ECB / SSM | G4: MAS | H4: BCBS | I4: FSB | J4: Proposed CPS XXXX position
A5: Legal character of the framework | B5: Binding prudential standards, but none addresses model risk as such. | C5: Supervisory guidance only, expressly non-enforceable; the sole binding instrument makes guidance non-binding. | D5: Supervisory statement; expectations, not Rulebook rules. | E5: Supervisory guideline; final but not effective until 1 May 2027. | F5: Supervisory guide interpreting binding CRR articles; the CRR is the law, the guide is not. | G5: Binding Notice for capital models; information paper and voluntary principles for AI. | H5: International principles; effect depends on domestic implementation. | I5: Analytical and consultative reports; expressly not standards. | J5: Binding cross-industry prudential standard, deliberately enforceable rather than advisory.
A6: Definition of a model | B6: Not defined on a cross-industry basis. | C6: Narrowed in April 2026 to complex methods applying statistical, economic or financial theories; excludes spreadsheet arithmetic, deterministic rules, and generative and agentic AI. | D6: Principle 1.1(a) sets out a definition firms should adopt as the basis for the scope of their framework, and expects consideration of quantitative methods falling outside it. | E6: Model definition expressly includes AI and machine learning. | F6: Internal models for regulatory capital; machine learning addressed as a technique within them. | G6: Capital models defined in Notice 637; AI models addressed separately. | H6: No general definition; BCBS 239 addresses risk data rather than models. | I6: Uses the OECD AI definition rather than a model definition. | J6: Broad function-based definition capturing deterministic actuarial and pricing calculations, which the US now excludes.
A7: Non-model quantitative tools | B7: Not addressed. | C7: Expressly excluded from the model definition; no control obligation stated in the 2026 guidance. | D7: Principle 1.1 expects firms to consider quantitative methods falling outside the model definition. | E7: Addressed through the risk-based approach. | F7: Not separately addressed. | G7: Not separately addressed. | H7: Not addressed. | I7: Not addressed. | J7: Express requirement to identify material tools outside the definition and control them proportionately.
A8: Enterprise-wide scope | B8: Implicit in CPS 220 but model risk is not named as a material risk. | C8: Applies across the organisation; most relevant above $30bn total assets. | D8: Enterprise-wide, but only for firms with internal model approval. | E8: Enterprise-wide across all models regardless of source or purpose. | F8: Limited to internal models used for regulatory capital. | G8: Capital models; AI practices observed more broadly. | H8: Not applicable. | I8: Not applicable. | J8: Enterprise-wide across all models, all business lines and all APRA-regulated industries.
A9: Proportionality | B9: General principle across all standards; not linked to model risk. | C9: Risk-based; a 2025 bulletin confirms community banks need not validate annually. | D9: Tiering drives control intensity. | E9: Scope, scale and intensity commensurate with model risk (Principle 2.3). | F9: Materiality of the model within the capital framework. | G9: Risk materiality drives control intensity. | H9: Principles applied proportionately. | I9: Explicit proportionality by institution and use-case materiality. | J9: Proportionate by tier, with exceptions documented, time-bound, approved and reviewed.
A10: De minimis and scope relief | B10: No mechanism; model requirements apply only where a capital or actuarial standard reaches them. | C10: Models deemed immaterial may attract only identification and monitoring of the conditions under which their use could become material; the guidance also applies mainly above a $30bn entity threshold. | D10: Tiering determines control intensity; no separate de minimis category. | E10: Principle 2.3 scales scope, scale and intensity to model risk, but Principle 2.1 keeps all models within identification. | F10: Materiality assessment within the internal model framework; no de minimis category. | G10: Risk materiality drives control intensity. | H10: Not addressed. | I10: Proportionality by use-case materiality. | J10: Express de minimis determination at model level, confined to identification, inventory, ownership, classification and reassessment, with prohibited classes, an aggregate test and an anti-disaggregation limb.
A11: Model inventory | B11: No cross-industry obligation. | C11: Described as common industry practice rather than an expectation. | D11: Principle 1.2 requires a model inventory. | E11: Principle 2.1 requires identification and tracking of all models in use or recently decommissioned. | F11: Model register expected for internal models. | G11: Expected for capital models; inventories observed in AI practice. | H11: Not addressed. | I11: Documentation of AI identified as a sound practice. | J11: Complete, current, controlled enterprise inventory including embedded, third-party and recently decommissioned models, with minimum fields prescribed.
A12: Risk tiering | B12: No taxonomy; APS 113 distinguishes only by capital treatment. | C12: Model risk framed as inherent risk in the context of materiality, itself a function of exposure and purpose. | D12: Principle 1.3 model tiering. | E12: Principle 2.2 requires a model risk rating approach assessing key dimensions. | F12: Materiality assessment within the internal model framework. | G12: Risk materiality assessment central to AI control intensity. | H12: Not addressed. | I12: Materiality and risk assessment at inception and thereafter. | J12: Documented tiering on quantitative and qualitative factors, driving validation, monitoring, approval and reporting intensity.
A13: Board and senior accountability | B13: CPS 220 gives the Board the risk management framework; model risk not named. | C13: Roles and responsibilities with defined accountability, including conflicts between development and validation. | D13: Principle 2.1 Board responsibilities and 2.2 SMF accountability for the framework. | E13: Principle 1.1 on reporting structures and resourcing. | F13: Section 5 identification of management body and senior management. | G13: Board and senior management oversight in observed AI practice. | H13: Governance is BCBS 239 Principle 1. | I13: Sound Practices 1 and 2 on strategic direction, oversight, governance and accountability. | J13: Board approves the framework and appetite; a named senior executive is accountable for the framework; every model has a named owner.
A14: Development and conceptual soundness | B14: APS 113 for IRB models only. | C14: Section IV on model development, including purpose statement, user input and testing. | D14: Principle 3.1 model purpose and design; 3.3 development testing. | E14: Principle 3.3 on development processes with clear standards. | F14: Documentation and data governance sections of the overarching principles chapter. | G14: Notice 637 for capital models. | H14: Not addressed directly. | I14: Sound Practice 6 on selection. | J14: Documented development standards, conceptual soundness, consideration of alternatives, and recorded limitations for all material models.
A15: Data | B15: CPG 235 is a non-enforceable guide dating from 2013. | C15: Data quality, relevance and inputs assessed within development testing. | D15: Principle 3.2 the use of data. | E15: Principle 3.2 requires data suitable for the intended use. | F15: Section 3 data governance; separate guide on risk data aggregation and reporting. | G15: Data quality and representativeness prominent in AI practice. | H15: BCBS 239 sets fourteen principles on risk data aggregation and reporting. | I15: Sound Practice 7 on data governance. | J15: Data appropriateness as well as quality, lineage to source, and documented treatment of proxy, external and synthetic data.
... A32: Supervisory notification | B32: CPS 230 and CPS 234 set materiality criteria and timeframes. | C32: No model-specific notification requirement. | D32: Escalation within the framework; no notification rule. | E32: Supervisory engagement expected. | F32: Model change approval required from the supervisor for capital models. | G32: Notification for capital model changes. | H32: Not addressed. | I32: Not addressed. | J32: Cross-references CPS 230 and CPS 234 rather than creating a separate deadline, with early engagement expected on material model weakness.

Sheet Legal Status Matrix
A1: Legal status and scope matrix
A2: POLICY DEVELOPMENT DRAFT — NOT IN FORCE | Do not treat guidance, analytical reports or consultations as binding requirements. An overseas instrument is not binding in Australia in any case.
A4: Source ID | B4: Authority | C4: Instrument | D4: Published | E4: Effective | F4: Legal status | G4: Scope and exclusions | H4: Verification
A5: US-MRM-2026 | B5: OCC / FRB / FDIC | C5: Supervisory Guidance on Model Risk Management — interagency guidance issued as Federal Reserve SR 26-2, OCC Bulletin 2026-13 and FDIC FIL-15-2026 | D5: 17 April 2026 | E5: 17 April 2026 | F5: Interagency supervisory guidance. Expressly non-enforceable: it 'does not set forth enforceable standards or prescriptive requirements' and non-compliance 'will not result in supervisory criticism'. US supervisory guidance does not have the force and effect of law. | G5: Expected to be most relevant to banking organisations with over $30 billion in total assets. Organisations at or below that threshold are generally excluded, though the guidance may still be relevant where model exposure is significant. Generative AI and agentic AI models are expressly outside scope. | H5: Verified — primary source
A6: US-MRM-2011 | B6: OCC / FRB | C6: OCC Bulletin 2011-12 / Federal Reserve SR 11-7 — Supervisory Guidance on Model Risk Management | D6: 4 April 2011 | E6: Rescinded and superseded 17 April 2026 | F6: Superseded supervisory guidance. Rescinded by OCC Bulletin 2026-13 and superseded by Federal Reserve SR 26-2 on 17 April 2026. Was never a regulation. Retained here for provenance because it originated most of the discipline's architecture. | G6: Applied to all banking organisations supervised by the Federal Reserve and the OCC, taking into account size, nature and complexity. Adopted by the FDIC in June 2017 via FIL-22-2017. | H6: Verified — primary source
A7: US-SG-STATUS | B7: OCC / FRB / FDIC | C7: Use of supervisory guidance — 12 CFR Part 4 Subpart F (OCC), 12 CFR §262.7 and Part 262 Appendix A (Board), 12 CFR Part 302 Appendix A (FDIC) | D7: Codified 2021, following the 2018 interagency statement | E7: In force | F7: Codified regulation. Binding on the agencies, not on supervised institutions. Provides that supervisory guidance does not have the force and effect of law and that the agencies do not take enforcement action on the basis of guidance. | G7: The OCC, the Federal Reserve Board and the FDIC and their supervised institutions. | H7: Verified — primary source
A8: OCC-CB-2025 | B8: OCC | C8: OCC Bulletin 2025-26 — Model Risk Management: Clarification for Community Banks | D8: 6 October 2025 | E8: On issue | F8: Bulletin clarifying the application of existing supervisory guidance. Not a regulation. Not rescinded by OCC Bulletin 2026-13. | G8: OCC-supervised community banks. | H8: Verified — primary source
A9: OCC-HANDBOOK | B9: OCC | C9: Comptroller's Handbook — Model Risk Management booklet | D9: August 2021 | E9: Rescinded 17 April 2026 | F9: Examiner handbook booklet, rescinded by OCC Bulletin 2026-13. Was guidance for OCC examiners, not a regulation. | G9: OCC examiners assessing model risk management at supervised banks, including community banks. | H9: Verified — secondary source
A10: PRA-SS1-23 | B10: PRA | C10: SS1/23 — Model risk management principles for banks | D10: 17 May 2023; current version dated 16 April 2026 | E10: 17 May 2024 | F10: Supervisory statement setting out PRA expectations. Not a PRA Rulebook instrument and not binding law. | G10: UK-incorporated banks, building societies and PRA-designated investment firms with internal model approval to calculate regulatory capital requirements. Does not apply to insurers, credit unions, third-country branches or firms without internal model approval. | H10: Verified — primary source
A11: PRA-PS6-23 | B11: PRA | C11: PS6/23 — Model risk management principles for banks (Policy Statement) | D11: 17 May 2023 | E11: 17 May 2024 | F11: Policy statement. Explains the final policy and feedback; the operative expectations sit in SS1/23. | G11: As for SS1/23. | H11: Verified — primary source
A12: PRA-SS3-18 | B12: PRA | C12: SS3/18 — Model risk management principles for stress testing | D12: April 2018; current version dated April 2026 | E12: April 2018 | F12: Supervisory statement. PRA expectations, not binding law. | G12: Firms in scope of the PRA's stress testing framework. | H12: Verified — primary source
A13: OSFI-E23 | B13: OSFI | C13: Guideline E-23 — Model Risk Management (2027) | D13: 11 September 2025 | E13: 1 May 2027 | F13: Final supervisory guideline. Not yet in effect at the as-of date. Sound Business and Financial Practices category. | G13: Banks, foreign bank branches, life insurance and fraternal companies, property and casualty companies, and trust and loan companies. Does not apply to federally regulated pension plans. | H13: Verified — primary source
A14: OSFI-E23-2017 | B14: OSFI | C14: Guideline E-23 — Enterprise-Wide Model Risk Management for Deposit-Taking Institutions (2017) | D14: 30 September 2017 | E14: On issue | F14: Supervisory guideline. OSFI's guidance library presents the 2027 guideline as its replacement from 1 May 2027, but no express supersession clause was located in either the 2027 guideline or its covering letter, so the relationship is stated as OSFI presents it rather than as a quoted provision. | G14: Federally regulated deposit-taking institutions only. | H14: Verified — primary source
A15: OSFI-B10 | B15: OSFI | C15: Guideline B-10 — Third-Party Risk Management | D15: April 2023 | E15: 1 May 2024 | F15: Supervisory guideline. | G15: Federally regulated financial institutions. | H15: Verified — primary source
... A54: APRA-SPS515 | B54: APRA | C54: Prudential Standard SPS 515 Strategic Planning and Member Outcomes | D54: Current at the as-of date | E54: In force at the as-of date | F54: Binding prudential standard. | G54: RSE licensees. | H54: Verified — primary source

Sheet Requirements Register
A1: Draft CPS XXXX requirements register
A2: POLICY DEVELOPMENT DRAFT — NOT IN FORCE | Mandatory wording appears in bold in the Word standard; this sheet records provenance and rationale.
A4: ID | B4: Part | C4: Section | D4: Title | E4: Mandatory requirement | F4: Source IDs | G4: Provenance | H4: Rationale | I4: Policy choice? | J4: Legal flag? | K4: International principle | L4: CPG XXXX paragraphs
A5: M01 | B5: Part A — Application and interpretation | C5: 1. Application and scope | D5: Enterprise-wide application and retained accountability | E5: An APRA-regulated entity must identify, assess, manage, monitor and report model risk arising from every model that it develops, acquires, configures, deploys or relies upon, whether the model is built internally, supplied by a third party or embedded within another system, and remains accountable for that model risk irrespective of who developed or operates the model. | F5: US-MRM-2026, PRA-SS1-23, OSFI-E23, APRA-CPS220, ECB-GIM | G5: Extracted | H5: Every comparator applies model risk management on an enterprise basis and none permits accountability to follow the model out of the institution. | I5: No | J5: No | K5: US interagency guidance 2026 §III; PRA SS1/23 Principle 1; OSFI E-23 enterprise-wide MRM | L5: 15–16
A6: M02 | B6: Part A — Application and interpretation | C6: 1. Application and scope | D6: Definition of a model and of model risk | E6: An APRA-regulated entity must apply a documented definition of a model that captures any quantitative method, system or approach that applies statistical, economic, financial, actuarial or mathematical theories, techniques or assumptions to process input data into quantitative estimates, and must treat model risk as the potential for adverse consequences from decisions based on incorrect or misused model outputs. | F6: US-MRM-2026, PRA-SS1-23, OSFI-E23 | G6: Extracted + inferred | H6: A broad, function-based definition follows the PRA and OSFI approach. The United States narrowed its definition in April 2026 to complex methods only, expressly excluding spreadsheet arithmetic and deterministic rule-based processes; that narrowing is not adopted here because it would exclude actuarial and unit pricing calculations central to the Australian cross-industry perimeter. The divergence is deliberate and recorded. | I6: No | J6: No | K6: PRA SS1/23 Principle 1.1 Model definition; OSFI E-23 (2027) key terms; US interagency guidance 2026 §II (narrower — excludes deterministic and arithmetic methods) | L6: 8–12
A7: M03 | B7: Part A — Application and interpretation | C7: 1. Application and scope | D7: Quantitative tools that are not models | E7: An APRA-regulated entity must identify material quantitative decision tools that fall outside its model definition — being tools whose output is fully determined by their inputs and documented rules, without estimation, statistical inference or an embedded assumption about an uncertain quantity, and whose output does not determine a regulatory figure, a reported valuation or an amount attributable to a customer or beneficiary — record them, and apply controls proportionate to the risk they present. | F7: PRA-SS1-23, OSFI-E23 | G7: Extracted | H7: The PRA expressly requires firms to consider quantitative methods that fall outside the model definition; without this, a narrow model definition becomes a control gap. | I7: No | J7: No | K7: PRA SS1/23 Principle 1 (identification of non-model quantitative methods) | L7: 12–14
A8: M04 | B8: Part A — Application and interpretation | C8: 2. Proportionality | D8: Proportionality and controlled exceptions | E8: An APRA-regulated entity must apply this Prudential Standard in a manner proportionate to the materiality, complexity, autonomy and criticality of each model and to the size and business mix of the entity, must be able to demonstrate that the intensity of controls applied to each model reflects its model risk tier and that models of equivalent tier are treated consistently, and must document, time-bound, approve at an authority commensurate with the risk and periodically review any departure from its own model risk policies and standards. | F8: PRA-SS1-23, OSFI-E23, US-MRM-2026, APRA-CPS220, BCBS-239 | G8: Extracted + inferred | H8: Proportionality is universal across the comparators; the explicit control of exceptions is drawn from APRA's existing risk management architecture. | I8: No | J8: No | K8: PRA SS1/23 proportionality; OSFI E-23 risk-based application; US interagency guidance 2026 §II | L8: 17, 28–29
A9: M05 | B9: Part A — Application and interpretation | C9: 2. Proportionality | D9: De minimis models | E9: An APRA-regulated entity may determine that a model is de minimis, and apply to that model only the identification, inventory, ownership, classification and reassessment requirements of this Prudential Standard, where the entity has assessed and documented that an error in, or misuse of, the model could not have a material effect on its financial position, its regulatory obligations, its critical operations, or amounts or entitlements attributable to its customers or beneficiaries. The entity must record the determination and the reasoning for it, approve it at an authority commensurate with the risk, assess whether models individually determined to be de minimis are material in aggregate, and reassess each determination on the occurrence of a trigger event and at a frequency set out in its model risk policy. | F9: OSFI-E23, PRA-SS1-23, US-MRM-2026, APRA-CPS220 | G9: Extracted + inferred | H9: Each comparator relieves low-consequence models of the full lifecycle while keeping them within identification. The 2026 US guidance states that where models are deemed immaterial, model risk management may consist of identifying those models and monitoring the conditions under which their use may become material. OSFI reaches the same result through Principles 2.1 and 2.3. The aggregate test, the prohibited classes and the anti-disaggregation limb are drafting choices that close the obvious routes to misuse of the exception. | I9: Yes | J9: No | K9: OSFI E-23 (2027) Principle 2.3 (scope, scale and intensity commensurate with model risk) read with Principle 2.1 (identify and track all models); PRA SS1/23 Principle 1.3 Model tiering; US interagency guidance 2026 §III (models deemed immaterial) | L9: 22–27
A10: M06 | B10: Part B — Governance and accountability | C10: 3. Board and senior management | D10: Board oversight of model risk | E10: The Board of an APRA-regulated entity must approve the model risk management framework and the entity's appetite for model risk, and must satisfy itself that model risk is being managed within that appetite and that it receives information sufficient to form that judgement. | F10: US-MRM-2026, PRA-SS1-23, OSFI-E23, APRA-CPS220, ECB-GIM | G10: Extracted | H10: Board approval of the framework and appetite is common to every comparator. | I10: No | J10: No | K10: PRA SS1/23 Principle 2 (governance); US interagency guidance 2026 §VI; OSFI E-23 governance | L10: 32–33, 35
A11: M07 | B11: Part B — Governance and accountability | C11: 3. Board and senior management | D11: Senior accountability for the framework | E11: An APRA-regulated entity must assign accountability for the design, implementation and effectiveness of the model risk management framework to a named senior executive with sufficient authority, independence from model development and business sponsorship, and resources to discharge it. | F11: PRA-SS1-23, US-MRM-2026, OSFI-E23, APRA-CPS220 | G11: Extracted | H11: The PRA allocates model risk management to a senior management function; OSFI and the US guidance require clear senior ownership. | I11: No | J11: Yes | K11: PRA SS1/23 Principle 2 (senior management function accountability); OSFI E-23 accountability | L11: 36–37
A12: M08 | B12: Part B — Governance and accountability | C12: 3. Board and senior management | D12: Model ownership and defined lifecycle roles | E12: An APRA-regulated entity must assign, for each model, a model owner accountable for the model throughout its lifecycle, and must define the roles, responsibilities and required independence of developers, validators, approvers, users and those responsible for monitoring. Where development, validation, approval or monitoring is performed by another member of the entity's group or by a related body corporate, the entity must satisfy itself that the work meets the requirements of this Prudential Standard and must retain the ability to direct, challenge and obtain evidence of it. | F12: US-MRM-2026, OSFI-E23, PRA-SS1-23, ECB-GIM | G12: Extracted | H12: Role definition with named model owners is explicit in the US, Canadian and ECB material. | I12: No | J12: No | K12: US interagency guidance 2026 §VI (roles and responsibilities); OSFI E-23 (2027) §A.4, defining Model Owner, Model Developer, Model Reviewer, Model Approver, Model User and Model Stakeholder; ECB guide §5 | L12: 38–39
A13: M09 | B13: Part B — Governance and accountability | C13: 4. Capability and independence | D13: Capability, resourcing and independence | E13: An APRA-regulated entity must maintain personnel, skills, tools and organisational arrangements sufficient to develop, use, validate, challenge and assure its models, with validation performed by persons who are independent of, and not accountable to, those who developed the model or who sponsor its business use. | F13: US-MRM-2026, PRA-SS1-23, OSFI-E23, ECB-GIM, MAS-AIMRM-2024 | G13: Extracted | H13: Independent validation is a core element of every comparator regime. | I13: No | J13: No | K13: US interagency guidance 2026 §V; PRA SS1/23 Principle 4.1; PRA SS1/23 Principle 4; ECB internal validation | L13: 40–42
A14: M10 | B14: Part C — Framework, appetite and policy | C14: 5. Model risk management framework | D14: Integrated model risk management framework | E14: An APRA-regulated entity must maintain a documented model risk management framework, integrated with its risk management framework, that covers model identification, inventory, tiering, development, data, testing, validation, approval, implementation, use, monitoring, change, limitations, remediation, decommissioning, reporting and assurance. | F14: PRA-SS1-23, OSFI-E23, US-MRM-2026, APRA-CPS220, APRA-CPS230 | G14: Extracted | H14: A documented enterprise framework is required by each of the comparator regimes. | I14: No | J14: No | K14: PRA SS1/23 Principle 2; OSFI E-23 enterprise framework; US interagency guidance 2026 §VI | L14: 43–44
A15: M11 | B15: Part C — Framework, appetite and policy | C15: 5. Model risk management framework | D15: Model risk appetite and limits | E15: An APRA-regulated entity must define its appetite for model risk, express it in terms capable of being monitored, and establish limits, thresholds and escalation triggers against which model risk is measured and reported. | F15: PRA-SS1-23, OSFI-E23, APRA-CPS220, US-MRM-2026 | G15: Extracted + inferred | H15: Comparators require a risk appetite for model risk; requiring it to be measurable is a drafting choice that makes the obligation supervisable. | I15: Yes | J15: No | K15: PRA SS1/23 Principle 2 (risk appetite); OSFI E-23 framework aligned to risk appetite | L15: 45–47
... A49: M45 | B49: Part J — Aggregate risk, records and assurance | C49: 30. APRA engagement | D49: Notification and provision of information to APRA | E49: An APRA-regulated entity must notify APRA as soon as practicable, and within the timeframe applicable under CPS 230 or CPS 234 where the event also falls within those standards, of a model failure or model risk event that has, or is likely to have, a material impact on its financial position, on amounts credited to or debited from the accounts of its customers or beneficiaries, on its regulatory reporting or on its ability to meet its prudential obligations, and must provide APRA with information relating to its models and model risk management where APRA requires it in writing. Where APRA requires an entity, under another prudential standard, to appoint an auditor or independent party to review and report to APRA on a matter that includes its models or its model risk management, the entity must support that review and must provide the reviewer with access to the models, data, documentation, systems and personnel reasonably required for the matters APRA has specified. | F49: APRA-CPS230, APRA-CPS234, APRA-CPS220, APRA-APS220, APRA-APS310, APRA-GPS310, APRA-LPS310, APRA-HPS310, APRA-SPS310, OSFI-E23 | G49: Extracted + inferred; legal drafting required | H49: Deliberately cross-references existing notification architecture rather than proposing a separate model risk deadline that would conflict with it. | I49: No | J49: Yes | K49: CPS 230 incident notification; OSFI E-23 supervisory engagement | L49: 130–134, 142–143

Sheet Requirement Test
A1: Requirement-by-authority challenge
A2: POLICY DEVELOPMENT DRAFT — NOT IN FORCE | 'Strong support' means the authority's material supports the requirement's substance. It does not mean the requirement is binding anywhere.
A4: ID | B4: Requirement | C4: APRA | D4: OCC/Fed | E4: PRA | F4: OSFI | G4: ECB | H4: MAS | I4: BCBS | J4: FSB | K4: Overall test result | L4: Verification sources
A5: M01 | B5: Enterprise-wide application and retained accountability | C5: Strong support | D5: Strong support | E5: Strong support | F5: Strong support | G5: Strong support | H5: Not addressed | I5: Not addressed | J5: Not addressed | K5: Pass — supported and status-qualified | L5: US-MRM-2026, PRA-SS1-23, OSFI-E23, APRA-CPS220, ECB-GIM
A6: M02 | B6: Definition of a model and of model risk | C6: Not addressed | D6: Diverges | E6: Strong support | F6: Strong support | G6: Not addressed | H6: Not addressed | I6: Not addressed | J6: Not addressed | K6: Pass — supported and status-qualified | L6: US-MRM-2026, PRA-SS1-23, OSFI-E23 | OCC/Fed: The April 2026 guidance narrows the definition to complex methods and excludes spreadsheet arithmetic, deterministic rules and generative and agentic AI. CPS XXXX does not follow.
A7: M03 | B7: Quantitative tools that are not models | C7: Not addressed | D7: Diverges | E7: Strong support | F7: Strong support | G7: Not addressed | H7: Not addressed | I7: Not addressed | J7: Not addressed | K7: Pass — supported and status-qualified | L7: PRA-SS1-23, OSFI-E23 | OCC/Fed: Expressly excludes such tools from the model definition and states no control obligation for them.
A8: M04 | B8: Proportionality and controlled exceptions | C8: Strong support | D8: Strong support | E8: Strong support | F8: Strong support | G8: Not addressed | H8: Not addressed | I8: Strong support | J8: Not addressed | K8: Pass — supported and status-qualified | L8: PRA-SS1-23, OSFI-E23, US-MRM-2026, APRA-CPS220, BCBS-239
A9: M05 | B9: De minimis models | C9: Strong support | D9: Strong support | E9: Strong support | F9: Strong support | G9: Not addressed | H9: Not addressed | I9: Not addressed | J9: Not addressed | K9: Pass as policy proposal — consult and cost-benefit test | L9: OSFI-E23, PRA-SS1-23, US-MRM-2026, APRA-CPS220
A10: M06 | B10: Board oversight of model risk | C10: Strong support | D10: Strong support | E10: Strong support | F10: Strong support | G10: Strong support | H10: Not addressed | I10: Not addressed | J10: Not addressed | K10: Pass — supported and status-qualified | L10: US-MRM-2026, PRA-SS1-23, OSFI-E23, APRA-CPS220, ECB-GIM
A11: M07 | B11: Senior accountability for the framework | C11: Strong support | D11: Strong support | E11: Strong support | F11: Strong support | G11: Not addressed | H11: Not addressed | I11: Not addressed | J11: Not addressed | K11: Conditional pass — legal drafting required | L11: PRA-SS1-23, US-MRM-2026, OSFI-E23, APRA-CPS220
A12: M08 | B12: Model ownership and defined lifecycle roles | C12: Not addressed | D12: Strong support | E12: Strong support | F12: Strong support | G12: Strong support | H12: Not addressed | I12: Not addressed | J12: Not addressed | K12: Pass — supported and status-qualified | L12: US-MRM-2026, OSFI-E23, PRA-SS1-23, ECB-GIM
A13: M09 | B13: Capability, resourcing and independence | C13: Not addressed | D13: Strong support | E13: Strong support | F13: Strong support | G13: Strong support | H13: Strong support | I13: Not addressed | J13: Not addressed | K13: Pass — supported and status-qualified | L13: US-MRM-2026, PRA-SS1-23, OSFI-E23, ECB-GIM, MAS-AIMRM-2024
A14: M10 | B14: Integrated model risk management framework | C14: Strong support | D14: Strong support | E14: Strong support | F14: Strong support | G14: Not addressed | H14: Not addressed | I14: Not addressed | J14: Not addressed | K14: Pass — supported and status-qualified | L14: PRA-SS1-23, OSFI-E23, US-MRM-2026, APRA-CPS220, APRA-CPS230
A15: M11 | B15: Model risk appetite and limits | C15: Strong support | D15: Strong support | E15: Strong support | F15: Strong support | G15: Not addressed | H15: Not addressed | I15: Not addressed | J15: Not addressed | K15: Pass as policy proposal — consult and cost-benefit test | L15: PRA-SS1-23, OSFI-E23, APRA-CPS220, US-MRM-2026
... A49: M45 | B49: Notification and provision of information to APRA | C49: Strong support | D49: Not addressed | E49: Not addressed | F49: Strong support | G49: Not addressed | H49: Not addressed | I49: Not addressed | J49: Not addressed | K49: Conditional pass — legal drafting required | L49: APRA-CPS230, APRA-CPS234, APRA-CPS220, APRA-APS220, APRA-APS310, APRA-GPS310, APRA-LPS310, APRA-HPS310, APRA-SPS310, OSFI-E23

Sheet Traceability
A1: Guidance-to-requirement traceability
A2: POLICY DEVELOPMENT DRAFT — NOT IN FORCE | Every numbered paragraph of the draft practice guide, and the requirement it supports.
A4: CPG XXXX paragraph | B4: Chapter | C4: Guidance text | D4: Supports CPS XXXX | E4: Source attribution | F4: Verification note
A5: 1 | B5: Introduction | C5: This guide is structured to follow CPS XXXX. Each chapter opens with the requirements it supports, so that a reader working from the standard can find the corresponding guidance, and a reader working from the guidance can identify the obligation it explains. | D5: —
A6: 2 | B6: Introduction | C6: Guidance in this guide is drawn from Australian prudential requirements and from the model risk frameworks of comparable authorities. International sources are labelled by legal status: [B] binding in its home jurisdiction, [SE] supervisory expectation, [G] guidance, [PB] proposed or consultative, and [A] analytical or advisory. An overseas instrument is not binding in Australia whatever its status at home, and is used here only to inform expectations under CPS XXXX. | D6: — | E6: Status classification follows Annex D of this guide and the source register in the accompanying assessment workbook.
A7: 3 | B7: Introduction | C7: APRA expects this guide to be applied proportionately. An entity with a small number of vendor models and one with several hundred internally developed models across banking, insurance and superannuation businesses face the same obligations but will meet them very differently. | D7: —
A8: 4 | B8: Introduction | C8: This guide does not create obligations, does not vary CPS XXXX, and does not limit APRA's discretion in supervising an entity. Where this guide and CPS XXXX appear to differ, CPS XXXX prevails. | D8: —
A9: 5 | B9: Introduction | C9: Regulated entities have increased their reliance on models faster than they have increased their capacity to govern them. Models now determine capital, provisions, valuations, insurance liabilities, unit prices, credit decisions, fraud interventions and member outcomes. The consequence of a model being wrong has grown with the consequence of the decisions it drives. | D9: —
A10: 6 | B10: Introduction | C10: Model risk has historically been managed inside the frameworks for the risks the models measure — credit models under credit risk, valuation models under market risk — with the result that no one is accountable for the risk that the measurement itself is wrong. Comparable authorities have moved model risk into its own discipline for this reason. | D10: — | E10: Source: PRA SS1/23 [SE]. OSFI Guideline E-23 (2027) [SE]. US interagency guidance on model risk management, SR 26-2 / OCC 2026-13 / FDIC FIL-15-2026 [SE].
A11: 7 | B11: Introduction | C11: The most consequential failures observed internationally have rarely been mathematical. They have been failures of scope, where a model was not known to exist; of use, where a sound model was applied to a purpose it was not built for; of implementation, where the deployed model differed from the approved one; and of challenge, where a weakness was identified and not acted upon. | D11: —
A12: 8 | B12: Scope — what is a model | C12: An entity should adopt a single enterprise definition of a model and apply it consistently. Fragmented definitions applied differently by business line produce inconsistent coverage and make aggregate model risk impossible to assess. | D12: M02
A13: 9 | B13: Scope — what is a model | C13: It is useful to think of a model as having three parts: an information input component that delivers data and assumptions, a processing component that transforms inputs into estimates, and a reporting component that translates the estimates into information a business can use. Each part can fail independently, and a failure in the first or third is as consequential as a failure in the second. | D13: M02 | E13: Source: PRA SS1/23 Principle 1.1 Model definition [SE]. OSFI Guideline E-23 (2027), key terms [SE]. The three-component description originated in the 2011 United States interagency guidance, which was rescinded on 17 April 2026; the description remains analytically useful and is retained here on that basis rather than as a current citation. | F13: Verification: the United States interagency guidance was revised on 17 April 2026 (SR 26-2, OCC Bulletin 2026-13, FDIC FIL-15-2026), rescinding the 2011 guidance. The 2026 definition is narrower — a 'complex' quantitative method applying statistical, economic or financial theories, expressly excluding simple arithmetic such as spreadsheet calculations and deterministic rule-based processes, and expressly excluding generative and agentic AI. CPS XXXX does not adopt that narrowing, for the reasons given in the standard. The divergence is deliberate.
A14: 10 | B14: Scope — what is a model | C14: The definition is function-based. Whether the processing component is a linear regression, a deterministic actuarial projection, a decision tree, a gradient-boosted ensemble or a large language model does not change whether the tool is a model. Defining scope by technology creates a perimeter that moves every time the technology does. | D14: M02
A15: 11 | B15: Scope — what is a model | C15: Quantitative estimates include forecasts, valuations, risk measures, scores, rankings, classifications and probabilities. A tool that produces a categorical output is a model where the classification rests on an estimate of an uncertain quantity — a score, a probability or a predicted class. A tool that reaches a categorical output by applying documented rules to its inputs, with no such estimate, falls outside the definition and is dealt with under M03. | D15: M02
A16: 12 | B16: Scope — what is a model | C16: Entities should expect genuine borderline cases and should decide them on a documented basis. The practical question is whether uncertainty in the method could produce a materially wrong answer that a user would not detect. Where it could, the tool should generally be managed as a model. | D16: M02, M03
A17: 13 | B17: Scope — what is a model | C17: Tools that fall outside the definition but drive material decisions should still be controlled. Complex spreadsheets, rules engines, allocation keys, pricing calculators and end-user computing tools fail in the same ways models fail — stale assumptions, broken links, undocumented changes, key-person dependency — without the benefit of the model lifecycle. | D17: M03 | E17: Source: PRA SS1/23 Principle 1.1, which expects firms to consider quantitative methods falling outside the model definition [SE]. | F17: Verification: PRA SS1/23's five principles and 23 sub-principles were extracted verbatim from the primary supervisory statement. Principle 1 is 'Model identification and model risk classification' and Principle 5 is 'Model risk mitigants'. An earlier draft in this project described Principle 5 as 'reporting'; that was incorrect and has been corrected here.
A18: 14 | B18: Scope — what is a model | C18: Controls for non-model quantitative tools need not replicate the model lifecycle. Identified ownership, version control, access restriction, documented logic, change control and periodic verification that the tool still performs as intended will usually be proportionate. | D18: M03
A19: 15 | B19: Scope — what is a model | C19: A model is within scope because the entity relies on its output, not because the entity wrote it. Vendor models, models embedded in core banking, actuarial or treasury platforms, models inherited through acquisition, models operated by a service provider and models supplied by a parent or affiliate are all within scope. | D19: M01, M32
A20: 16 | B20: Scope — what is a model | C20: Entities should be alert to models that arrive without a procurement decision — a feature enabled in an existing platform, an analytics capability switched on by a provider, or a tool adopted by a business team. These are the models least likely to appear in the inventory and least likely to have been assessed. | D20: M01
A21: 17 | B21: Proportionality and model risk tiering | C21: Tiering is the mechanism by which proportionality is made operational. It converts a general statement that controls should reflect risk into a specific determination of how much development evidence, validation depth, monitoring frequency, approval seniority and reporting each model attracts. | D21: M04, M15 | E21: Source: PRA SS1/23 Principle 1.3 Model tiering [SE]. OSFI Guideline E-23 (2027) Principle 2.2, on establishing a model risk rating approach that assesses key dimensions of model risk [SE].
A22: 18 | B22: Proportionality and model risk tiering | C22: A tiering methodology should combine quantitative and qualitative factors. Quantitative factors typically include the size of the exposure, balance, provision, capital number or customer population the model influences. Qualitative factors include complexity, transparency, data quality, degree of automation, reversibility of the consequence and the availability of an alternative. | D22: M15
A23: 19 | B23: Proportionality and model risk tiering | C23: Materiality of use should dominate technical complexity. A simple deterministic calculation that sets a regulatory capital figure or a unit price warrants a higher tier than a sophisticated model used for internal management reporting. Tiering schemes anchored to methodological sophistication systematically under-govern the models that matter most. | D23: M15
A24: 20 | B24: Proportionality and model risk tiering | C24: The number of tiers matters less than the difference between them. Three tiers applied with genuine differentiation are more useful than five tiers that attract broadly similar treatment. If the tiering scheme does not change what actually happens to a model, it is documentation rather than control. | D24: M15
A25: 21 | B25: Proportionality and model risk tiering | C25: Entities should monitor the distribution of models across tiers over time. A population that migrates steadily downward, or in which very few models occupy the highest tier, warrants examination of whether the criteria are being applied as designed. | D25: M15
A26: 22 | B26: Proportionality and model risk tiering | C26: CPS XXXX permits an entity to determine that a model is de minimis and to apply to it only the identification, inventory, ownership, classification and reassessment requirements. The determination turns on consequence: whether the entity could be materially wrong, or materially unfair to a customer or beneficiary, if the model were wrong and the error went undetected. | D26: M05
A27: 23 | B27: Proportionality and model risk tiering | C27: It is not a determination about size, complexity, cost or how long a model has been in use. A simple model that has run without incident for a decade is not de minimis if an error in it would misstate a provision. Conversely a sophisticated model used to prioritise internal workflow may well be. | D27: M05 | E27: Source: US interagency guidance 2026 §III, which states that where models are deemed immaterial, model risk management may consist of identifying those models and monitoring the conditions under which their use may become material [SE]. OSFI Guideline E-23 (2027) Principle 2.3, read with Principle 2.1 [SE]. PRA SS1/23 Principle 1.3 Model tiering [SE].
A28: 24 | B28: Proportionality and model risk tiering | C28: A de minimis model stays in the inventory. That is the point on which the exception depends: an entity that has removed a model from the inventory cannot demonstrate that the determination was ever made, still less that it remains correct. Entities should treat the de minimis population as a reportable category rather than as an absence. | D28: M05, M14
A29: 25 | B29: Proportionality and model risk tiering | C29: Certain models cannot be de minimis whatever the entity's assessment. These are models determining a regulatory capital requirement, a provision, a technical or insurance liability, a valuation reported in the financial statements, a unit price or another amount attributable to a customer or beneficiary, and models supporting a critical operation. The consequence of error in these classes is realised directly and is frequently irreversible. | D29: M05
A30: 26 | B30: Proportionality and model risk tiering | C30: Two failure modes deserve specific attention. The first is aggregation: models that are individually immaterial can matter collectively, particularly where they feed the same process, share a data source or rest on a common assumption. The entity should examine the population, not only the individual determinations. The second is disaggregation: splitting a model so that each component falls below the threshold, which defeats the exception rather than satisfying it. | D30: M05
A31: 27 | B31: Proportionality and model risk tiering | C31: A determination attaches to a use, not to a model in the abstract. Where a model that was de minimis for one purpose begins to be relied on for another, the determination should be revisited before the new use begins rather than at the next scheduled review. | D31: M05, M16 | F31: Verification: the de minimis mechanism is drawn from the treatment of immaterial models in the 2026 United States interagency guidance and from OSFI Principles 2.1 and 2.3, which relieve low-risk models of the full lifecycle while keeping them within identification. The prohibited classes, the aggregate test and the anti-disaggregation limb are Australian drafting choices and are identified as a policy design choice in the assessment workbook.
A32: 28 | B32: Proportionality and model risk tiering | C32: Reduced controls should be a decision rather than an omission. An exception should identify the provision of the entity's own policies or standards not being met, the reason, the compensating control, the approver, the expiry date and the review point. It cannot except the entity from a requirement of CPS XXXX: only APRA may do that, under paragraph A5. | D32: M04
A33: 29 | B33: Proportionality and model risk tiering | C33: An exception register in which items have no expiry, or are routinely extended, indicates that the entity has adopted a lower standard rather than granted an exception. APRA supervisors may examine the age profile of exceptions as an indicator of framework effectiveness. | D33: M04 | F33: Verification: proportionality is expressly provided for in the PRA, OSFI and US frameworks. The specific expectation that exceptions be time-bound with recorded compensating controls is drawn from APRA's existing risk management architecture rather than from a comparator instrument, and is identified in the assessment workbook as a policy design choice.
A34: 30 | B34: Proportionality and model risk tiering | C34: Tiers should be reassessed on a defined cycle and on the occurrence of trigger events. Triggers should include material change to the model, its data, its purpose or its user base; significant growth in the exposure or population it covers; deterioration in performance; and changes the entity did not initiate, such as a vendor version release or a change in an upstream data definition. | D34: M16
A35: 31 | B35: Proportionality and model risk tiering | C35: Reliance can grow without any change to the model. A model built for a small portfolio that is progressively applied to a larger one has become more material without being touched, and a reassessment cycle driven only by model change will not detect this. | D35: M16
A36: 32 | B36: Governance and accountability | C36: The Board should understand what the entity relies on models to do, where that reliance is concentrated, what the consequences of failure would be, how failure would be detected, and what would happen next. It is not expected to understand model methodology. | D36: M06 | E36: Source: PRA SS1/23 Principle 2 Governance, and Principle 2.1 Board of directors' responsibilities [SE]. OSFI Guideline E-23 (2027) Outcome 1 and Principle 1.1 [SE]. US interagency guidance 2026 §VI, governance and controls [SE]. CPS 220 Risk Management [B].
A37: 33 | B37: Governance and accountability | C37: Board reporting should support that understanding. Useful content includes the tiering profile and its movement, validation coverage and overdue validations against tier, unresolved high-severity findings and their age, material limitations accepted and the compensating controls relied on, the aggregate size and direction of overlays, model incidents, and concentration of reliance on individual providers or methods. | D37: M06, M13
A38: 34 | B38: Governance and accountability | C38: Reporting should aggregate rather than enumerate. A schedule of individual model issues does not tell the Board whether model risk is rising or falling. Trend, concentration and coverage are more informative than counts. | D38: M13
A39: 35 | B39: Governance and accountability | C39: For a smaller entity, model risk reporting may sit within existing risk reporting rather than in a standalone pack, provided the Board receives the substance and can identify model risk as a distinct matter. | D39: M06
A40: 36 | B40: Governance and accountability | C40: A single senior executive should be accountable for the framework itself — its coverage, its consistency of application and its effectiveness. This is distinct from accountability for individual models, and exists so that framework-level failures have an owner. | D40: M07 | E40: Source: PRA SS1/23 Principle 2.2, SMF accountability for the model risk management framework [SE]. OSFI Guideline E-23 (2027) Principle 1.1 [SE].
A41: 37 | B41: Governance and accountability | C41: The accountable executive should be positioned to require change. Accountability without the authority to direct remediation, or without independence from the businesses whose models are being governed, is unlikely to be effective. | D41: M07 | F41: Verification: the PRA allocates model risk management framework accountability to a designated senior management function. The precise interaction with the Australian accountability regime requires legal settlement and is flagged in Annex F of CPS XXXX.
A42: 38 | B42: Governance and accountability | C42: Each model should have a named owner accountable for it being fit for its approved purpose, for its documentation being current, for its performance being monitored, for its limitations being communicated to users, and for the remediation of findings. Ownership recorded in the inventory but not exercised is not ownership. | D42: M08
A43: 39 | B43: Governance and accountability | C43: Where several businesses use the same model, the entity should distinguish ownership of the model from ownership of each use. The model can be sound while a particular use of it is not, and the two failures require different responses. | D43: M08 | E43: Source: US interagency guidance 2026 §VI, roles and responsibilities [SE]. OSFI Guideline E-23 (2027) Principle 1.1 [SE]. ECB Guide to internal models, internal governance [SE].
A44: 40 | B44: Governance and accountability | C44: Validation should be performed by people who did not build the model and who do not report to those who did or to the business sponsoring its use. Where a standing independent validation function is not practicable, independence can still be achieved — by drawing on qualified people elsewhere in the entity or group who were not involved in development, by engaging an external provider, or by escalating the review to a forum that is independent of the sponsoring business. | D44: M09
A45: 41 | B45: Governance and accountability | C45: Independence is a matter of incentive as much as of reporting line. Where a validator's workload, progression or remuneration depends on models being approved, the control is compromised regardless of the organisational structure. | D45: M09
A46: 42 | B46: Governance and accountability | C46: Smaller entities may achieve independence by using qualified people from elsewhere in the entity or group who were not involved in development, or by engaging an external provider. An entity that outsources validation should retain enough capability to scope the work, understand the findings and challenge the conclusions. | D46: M09 | E46: Source: US interagency guidance 2026 §V [SE]. PRA SS1/23 Principle 4.1 The independent validation function [SE]. ECB Guide to internal models, internal validation [SE].
A47: 43 | B47: Framework, appetite and policy | C47: The framework should treat model risk as a risk in its own right. Treating it as a category of operational risk tends to produce incident-driven management after a failure rather than lifecycle management designed to prevent one. | D47: M10 | E47: Source: PRA SS1/23 Principle 2 [SE]. OSFI Guideline E-23 (2027) Outcome 1, that model risk is well understood and managed across the enterprise [SE]. CPS 220 Risk Management [B].
A48: 44 | B48: Framework, appetite and policy | C48: The framework should connect to, rather than duplicate, the entity's arrangements for data risk, information security, operational risk, change management, service provider management and internal audit. Where an entity operates a separate AI risk framework, the boundary between the two should be explicit. | D48: M10
A49: 45 | B49: Framework, appetite and policy | C49: A model risk appetite should be capable of being breached. An appetite expressed only as a statement of intent cannot be monitored and therefore cannot constrain behaviour. | D49: M11
A50: 46 | B50: Framework, appetite and policy | C50: Measurable expressions available to most entities include tolerance for the proportion of high-tier models with a current validation, the permitted number and age of unresolved high-severity findings, limits on the aggregate size of overlays relative to the modelled figure, and constraints on models operating outside approved conditions of use. | D50: M11
A51: 47 | B51: Framework, appetite and policy | C51: Entities that cannot yet quantify aggregate model risk should say so, use coverage and qualitative measures in the interim, and set out how they intend to develop the capability. An appetite deferred until quantification is available is an appetite that does not exist. | D51: M11, M42 | F51: Verification: a model risk appetite is expected by the PRA and OSFI. Requiring it to be expressed in monitorable terms is a drafting choice that makes the obligation supervisable, and is identified as a policy design choice in the assessment workbook.
A52: 48 | B52: Framework, appetite and policy | C52: Policies and standards should be applied consistently across the entity. Where different businesses apply materially different development, documentation or validation standards to models of equivalent tier, the entity should be able to justify the difference on risk grounds rather than on history or convenience. | D52: M12 | E52: Source: PRA SS1/23 Principle 2.3 Policies and procedures [SE]. OSFI Guideline E-23 (2027) Principle 3.1 [SE]. US interagency guidance 2026 §VI, governance and controls [SE].
A53: 49 | B53: Framework, appetite and policy | C53: Policies should be reviewed at least annually and version-controlled, with the substance of changes recorded. A policy library in which the current version cannot be established, or in which superseded versions remain in circulation, undermines the framework it documents. | D53: M12
A54: 50 | B54: Identification and inventory | C54: The inventory is the foundation of the framework. No requirement in CPS XXXX can be demonstrated for a model the entity does not know it has, and inventory completeness is therefore the first thing an entity should be able to evidence. | D54: M14 | E54: Source: PRA SS1/23 Principle 1.2 Model inventory [SE]. OSFI Guideline E-23 (2027) Principle 2.1, on identifying and tracking all models in use or recently decommissioned [SE]. US interagency guidance 2026 §VI, model inventory [SE].
A55: 51 | B55: Identification and inventory | C55: Identification requires active discovery. Voluntary registration reliably under-reports, because the models least likely to be declared are those adopted without formal approval — precisely the population of greatest concern. | D55: M14
A56: 52 | B56: Identification and inventory | C56: Discovery mechanisms that entities have found effective include: | D56: M14
A57: 53 | B57: Identification and inventory | C57: The inventory should record decommissioned models where outputs they produced remain in force. A retired model that set a provision, a capital number, a customer price or an insurance liability that has not yet run off continues to carry model risk after the model itself has been switched off. | D57: M14
A58: 54 | B58: Identification and inventory | C58: Annex B of CPS XXXX sets out the minimum inventory fields. Entities should treat these as a floor. The inventory should be maintained as a controlled record with defined update responsibilities rather than as a periodically refreshed spreadsheet. | D58: M14 | F58: Verification: inventory obligations were confirmed from the primary text of the PRA, OSFI and US instruments. OSFI's express inclusion of recently decommissioned models is extracted from Principle 2.1 of Guideline E-23 (2027).
A59: 55 | B59: Development, data and documentation | C59: Conceptual soundness asks whether the chosen approach is appropriate for the intended purpose, given the data available and the conditions in which the model will operate. It is not answered by goodness of fit. A model that fits its development sample closely may be conceptually unsound if that sample is unrepresentative of the conditions of use. | D59: M17 | E59: Source: US interagency guidance 2026 §IV, model development and model use [SE]. PRA SS1/23 Principle 3.1 Model purpose and design [SE]. OSFI Guideline E-23 (2027) Principle 3.3 [SE].
A60: 56 | B60: Development, data and documentation | C60: Development should record the purpose the model is being built for, the design decisions taken, the theory or empirical basis for them, the variables considered and why they were retained or rejected, the assumptions on which the model depends, and the limitations that development did not resolve. | D60: M17
A61: 57 | B61: Development, data and documentation | C61: Reasonable alternatives should be considered and the choice recorded. Where a more transparent method would have performed acceptably, the entity should be able to explain why a less transparent one was preferred. This is not a presumption against complex methods; it is a record that the trade-off was made deliberately. | D61: M17
A62: 58 | B62: Development, data and documentation | C62: Development evidence should include the tests that were run and their results, including tests the model did not pass and how that was resolved. Documentation presenting only successful tests gives validation and approval an incomplete picture. | D62: M17
A63: 59 | B63: Development, data and documentation | C63: Data should be assessed for appropriateness as well as accuracy. Accurate data drawn from a population, product, geography or period unlike the one in which the model will be used produces confident and wrong answers, and is a more common failure than poor data quality. | D63: M18 | E63: Source: BCBS 239 Principles for effective risk data aggregation and risk reporting [G]. OSFI Guideline E-23 (2027) Principle 3.2, that data used to develop the model should be suitable for the intended use [SE]. CPG 235 Managing Data Risk [G]. ECB Guide on effective risk data aggregation and risk reporting [SE].
A64: 60 | B64: Development, data and documentation | C64: Entities should document data lineage to source for material models, so that a change in an upstream system or definition can be traced to the models it affects. Lineage that stops at the data warehouse does not support that assessment. | D64: M18
A65: 61 | B65: Development, data and documentation | C65: Where proxy or external data substitutes for insufficient internal data, the basis for considering the proxy suitable should be recorded and the sensitivity of the output to that choice should be tested. Proxies adopted at development frequently persist long after internal data has become available. | D65: M18
A66: 62 | B66: Development, data and documentation | C66: Synthetic data used in development or testing should be identified as such, with its generation method documented and its representativeness assessed. Testing a model on synthetic data generated from the same assumptions used to build it does not test those assumptions. | D66: M18, M34
A67: 63 | B67: Development, data and documentation | C67: The practical standard for documentation is reconstruction: a competent person who was not involved in the model's development should be able to pick up the documentation and reproduce its material results. Documentation that depends on the continued availability of the developer is a key-person dependency. | D67: M19 | E67: Source: US interagency guidance 2026 §VI, documentation [SE]. PRA SS1/23 Principle 3.5 Model development documentation [SE]. ECB Guide to internal models, documentation [SE].
A68: 64 | B68: Development, data and documentation | C68: Documentation should be maintained through the model's life. Documentation assembled in response to a validation cycle or a supervisory request describes the model as it is remembered rather than as it was built and changed. | D68: M19
A69: 65 | B69: Testing, validation and approval | C69: Development testing and validation are different exercises with different purposes. Development testing establishes whether the model works as its developers intended. Validation forms an independent view of whether it is fit to be relied upon. | D69: M20
A70: 66 | B70: Testing, validation and approval | C70: Pre-implementation testing should cover performance under expected conditions and under stressed, boundary and unrepresentative conditions; sensitivity to key assumptions and inputs; stability over time and across segments; and behaviour at the edges of the population the model will encounter. | D70: M20
A71: 67 | B71: Testing, validation and approval | C71: Testing should use data sufficiently independent of the data used to fit the model. Out-of-sample and, where possible, out-of-time testing should be standard for higher-tier models. | D71: M20 | E71: Source: US interagency guidance 2026 §IV, model testing [SE]. PRA SS1/23 Principle 3.3 Model development testing [SE].
A72: 68 | B72: Testing, validation and approval | C72: Validation should address three complementary components: conceptual soundness, including assessment of model design, key modelling choices, assumptions, data selection, construction and developmental evidence; outcomes analysis, comparing model outputs with corresponding real-world outcomes; and ongoing model monitoring, evaluating whether the model continues to perform as expected as products, exposures, activities, clients, data relevance or market conditions change. | D72: M22 | E72: Source: US interagency guidance 2026 §V, components of model validation [SE]. PRA SS1/23 Principle 4.2 Independent review, 4.3 Process verification and 4.4 Model performance monitoring [SE]. OSFI Guideline E-23 (2027) Principle 3.4 [SE].
A73: 69 | B73: Testing, validation and approval | C73: No component is sufficient alone. Conceptual soundness cannot detect deterioration after implementation. Outcomes analysis can detect deterioration but not explain it. Verification that the model was built and deployed as documented says nothing about whether the design was appropriate in the first place. | D73: M22
A74: 70 | B74: Testing, validation and approval | C74: Validation should test implementation as well as design — that the model as coded and running in production is the model as documented and approved. Differences in data definitions, rounding, treatment of missing values, library versions or execution order between environments can change results materially and are not detected by methodological review. | D74: M22, M25
A75: 71 | B75: Testing, validation and approval | C75: A validation report should reach an explicit conclusion on fitness for the intended use, with any conditions or limitations stated. A report that records observations without a conclusion leaves the approval decision without the input it was designed to receive. | D75: M22 | F75: Verification: the three components of validation are extracted from the current US interagency guidance, which is supervisory guidance rather than a regulation and is non-enforceable by its own terms. No fixed validation frequency is stated in this guide: the rescinded 2011 US guidance contained an at-least-annual periodic review expectation which the April 2026 guidance does not carry forward, and OCC Bulletin 2025-26 confirms that community banks are not required to validate annually. Setting cycle lengths is left to the entity, by tier.
A76: 72 | B76: Testing, validation and approval | C76: Effective challenge is critical and objective analysis by people with three attributes together: the expertise to identify model limitations, sufficient independence to maintain objectivity, and the organisational standing and influence to bring about change. Removing any one defeats the control while leaving its documentation intact. Entities should also attend to incentives, since a challenger rewarded for clearing models will not challenge for long. | D76: M23 | E76: Source: US interagency guidance 2026 §III, effective challenge [SE]. PRA SS1/23 Principle 4 Independent model validation [SE].
A77: 73 | B77: Testing, validation and approval | C77: Indicators that challenge is not effective include findings consistently closed by explanation rather than by change, findings downgraded in severity without new evidence, validation conclusions that soften late in the approval process, and validation functions whose resourcing is set by the businesses whose models they review. | D77: M23
A78: 74 | B78: Testing, validation and approval | C78: Entities should periodically assess whether challenge is working, rather than assuming it from the existence of a validation function. Analysis of finding closure routes, severity migration and elapsed time to remediation is more informative than validation completion rates. | D78: M23, M44
A79: 75 | B79: Testing, validation and approval | C79: Vendor validation reports, certifications and third-party audit opinions may inform the entity's validation. They do not discharge it, because they are not designed around the entity's data, portfolio, controls or intended use. An entity relying on them should record what they cover and what remains for the entity to test. | D79: M21, M32
A80: 76 | B80: Testing, validation and approval | C80: Approval should be of a specific model version for a specific purpose under specific conditions. Approval expressed in general terms leaves no basis on which to determine later whether the model is being used as approved. | D80: M24
A81: 77 | B81: Testing, validation and approval | C81: The approval record should identify the approved version, the permitted uses and users, any limits on application, the monitoring thresholds that apply, the limitations accepted and the compensating controls relied upon, and the date by which the model must be reviewed. | D81: M24 | E81: Source: OSFI Guideline E-23 (2027), model approval within the model lifecycle [SE]. ECB Guide to internal models [SE].
A82: 78 | B82: Testing, validation and approval | C82: Approval despite unresolved high-severity findings should be exceptional, time-bound, supported by compensating controls and escalated to the forum that set the model risk appetite. | D82: M24, M30
A83: 79 | B83: Implementation, use and change | C83: Implementation is an under-appreciated source of model failure. Validation focused on methodology will not detect that the production model differs from the approved one, and such differences arise routinely from environment, data pipeline and configuration differences rather than from deliberate change. | D83: M25
A84: 80 | B84: Implementation, use and change | C84: Entities should verify, before a model is relied upon in production, that it reproduces the approved model's results on a controlled set of cases, and should repeat that verification after material infrastructure or data pipeline change. | D84: M25 | E84: Source: Former SR 11-7 §IV, implementation — not carried forward as a separate heading in the 2026 guidance [SE]. OSFI Guideline E-23 (2027) Principle 3.5, that models should be deployed in an environment with quality and change control processes [SE]. PRA SS1/23 Principle 3.6 Supporting systems [SE].
A85: 81 | B85: Implementation, use and change | C85: Change assessment should consider the change both in isolation and cumulatively. A sequence of individually immaterial recalibrations can move a model materially away from the version that was validated, and change frameworks that assess only the increment will not detect this. | D85: M26
A86: 82 | B86: Implementation, use and change | C86: Changes the entity did not initiate are still changes to its model risk profile. A vendor version release, a change in an upstream data definition, a change in the composition of a portfolio the model is applied to, or a change in the regulatory basis of a calculation should each enter the change assessment. | D86: M26 | E86: Source: ECB Guide to internal models, management of model changes [SE]. OSFI Guideline E-23 (2027) Principle 3.5 [SE].
A87: 83 | B87: Implementation, use and change | C87: Misuse of a sound model is one of the two recognised sources of model risk and is frequently the less well controlled. Common patterns include applying a model built to rank relative risk to set absolute prices, applying a model developed on one portfolio to another, and continuing to rely on a model in conditions it was known not to cover. | D87: M27 | E87: Source: Former SR 11-7 §III, the two sources of model risk — the 2026 guidance retains the misuse limb [SE]. PRA SS1/23 Principle 3 [SE]. ECB Guide to internal models, use test [SE].
A88: 84 | B88: Implementation, use and change | C88: Users should be given the model's limitations, not merely have access to them. Limitations recorded in a validation report that users do not read are not communicated. Entities should consider embedding limitations and conditions of use in the systems through which users receive model output. | D88: M27
A89: 85 | B89: Implementation, use and change | C89: Adjustments to model output should be governed with the same discipline as the model. The basis, the quantification, the approver, the duration and the conditions for removal should each be recorded. | D89: M28 | E89: Source: PRA SS1/23 Principle 5.1 Process for applying post-model adjustments [SE]. ECB Guide to internal models, margin of conservatism [SE].
A90: 86 | B90: Implementation, use and change | C90: A persistent overlay in a consistent direction is evidence about the model rather than a correction to it. Where an entity has adjusted a model's output in the same direction for successive periods, the appropriate response is usually redevelopment rather than continued adjustment. | D90: M28
A91: 87 | B91: Implementation, use and change | C91: Overlays should be reported in aggregate. Individually approved adjustments can collectively become the dominant driver of a reported figure without any single approval having considered that effect. | D91: M28, M13 | F91: Verification: post-model adjustments are addressed expressly by PRA SS1/23 Principle 5.1, which defines them to include model overlays, management overlays and model overrides. The ECB addresses the same issue through the margin of conservatism framework for internal models.
A92: 88 | B92: Monitoring, mitigants and retirement | C92: Monitoring should test whether the conditions that made the model valid continue to hold, not only whether its output has moved. A model can produce stable output while the relationships it depends on have broken down. | D92: M29 | E92: Source: US interagency guidance 2026 §V, ongoing model monitoring [SE]. PRA SS1/23 Principle 4.4 Model performance monitoring [SE]. OSFI Guideline E-23 (2027) Principle 3.6 [SE].
A93: 89 | B93: Monitoring, mitigants and retirement | C93: Thresholds should be set in advance and linked to a defined response — investigation, escalation, restriction of use, revalidation, overlay or withdrawal. A threshold that produces a note rather than an action is not a control. | D93: M29
A94: 90 | B94: Monitoring, mitigants and retirement | C94: Monitoring should cover input data as well as output. Shifts in the distribution, completeness or definition of inputs frequently precede deterioration in output and provide earlier warning. | D94: M29
A95: 91 | B95: Monitoring, mitigants and retirement | C95: Compensating controls should be specific to the limitation they address. A general statement that outputs are subject to management review does not compensate for a known bias in a particular segment, because it does not direct attention to that segment. | D95: M30 | E95: Source: PRA SS1/23 Principle 5 Model risk mitigants, and Principle 5.2 Restrictions on model use [SE].
A96: 92 | B96: Monitoring, mitigants and retirement | C96: Entities should monitor how findings are closed. A high proportion closed by rationale, deferral or reclassification rather than by change indicates that remediation is not functioning, even where closure rates appear satisfactory. | D96: M30
A97: 93 | B97: Monitoring, mitigants and retirement | C97: An entity should know in advance what it would do if a material model became unusable — whether an alternative exists, how long it would take to bring into service, and what the interim basis for decisions would be. For models supporting a critical operation, this should be tested. | D97: M31 | E97: Source: OSFI Guideline E-23 (2027) Principle 3.6, model decommission [SE]. CPS 230 Operational Risk Management [B].
A98: 94 | B98: Monitoring, mitigants and retirement | C98: Decommissioning should address downstream models that consume the retired model's output, decisions and balances that remain in force, retained records, and the disposition of data. Retirement that switches off the model without addressing its residue leaves risk in place without an owner. | D98: M31
A99: 95 | B99: Third-party models | C99: A third-party model is subject to the same framework as an internally developed one. The entity's ability to inspect it is lower, which increases rather than reduces the work required to gain assurance. | D99: M32 | E99: Source: US interagency guidance 2026 §VII, vendor and other third-party products [SE]. PRA SS1/23 Principle 2.6 Use of externally developed models, third-party vendor products [SE]. OSFI Guideline E-23 (2027), third-party models [SE].
A100: 96 | B100: Third-party models | C100: Where a provider will not disclose methodology, the entity should intensify what it can do independently: benchmarking against an alternative, outcomes analysis on its own portfolio, sensitivity testing through controlled variation of inputs, and tighter conditions of use. Opacity should narrow the approved use, not widen the tolerance. | D100: M32
A101: 97 | B101: Third-party models | C101: An entity should not accept from a provider a level of opacity it would not accept from an internal development team for a model of the same tier. | D101: M32
...

Sheet Principles Register
A1: International principles register
A2: POLICY DEVELOPMENT DRAFT — NOT IN FORCE | Principle labels and titles reproduced as printed by the issuing authority. Confidence records whether the text was read in the primary document.
A4: Authority | B4: Instrument | C4: Label | D4: Title as printed | E4: Confidence
A5: PRA | B5: PRA SS1/23 — Model risk management principles for banks | C5: Principle 1 | D5: Model identification and model risk classification | E5: Verified — primary source
A6: PRA | B6: PRA SS1/23 — Model risk management principles for banks | C6: Principle 1.1 | D6: Model definition | E6: Verified — primary source
A7: PRA | B7: PRA SS1/23 — Model risk management principles for banks | C7: Principle 1.2 | D7: Model inventory | E7: Verified — primary source
A8: PRA | B8: PRA SS1/23 — Model risk management principles for banks | C8: Principle 1.3 | D8: Model tiering | E8: Verified — primary source
A9: PRA | B9: PRA SS1/23 — Model risk management principles for banks | C9: Principle 2 | D9: Governance | E9: Verified — primary source
A10: PRA | B10: PRA SS1/23 — Model risk management principles for banks | C10: Principle 2.1 | D10: Board of directors’ responsibilities | E10: Verified — primary source
A11: PRA | B11: PRA SS1/23 — Model risk management principles for banks | C11: Principle 2.2 | D11: SMF accountability for model risk management framework | E11: Verified — primary source
A12: PRA | B12: PRA SS1/23 — Model risk management principles for banks | C12: Principle 2.3 | D12: Policies and procedures | E12: Verified — primary source
A13: PRA | B13: PRA SS1/23 — Model risk management principles for banks | C13: Principle 2.4 | D13: Roles and responsibilities | E13: Verified — primary source
A14: PRA | B14: PRA SS1/23 — Model risk management principles for banks | C14: Principle 2.5 | D14: Internal Audit | E14: Verified — primary source
A15: PRA | B15: PRA SS1/23 — Model risk management principles for banks | C15: Principle 2.6 | D15: Use of externally developed models, third-party vendor products | E15: Verified — primary source
... A169: APRA | B169: Australian instruments carrying model governance obligations | C169: SPS 515 | D169: Strategic planning and member outcomes | E169: Verified — primary source

Sheet Statement Ledger
A1: Key-statement provenance ledger
A2: POLICY DEVELOPMENT DRAFT — NOT IN FORCE | Designed for fact checking. Every material assertion about an overseas framework appears here with its evidential basis.
A4: Statement ID | B4: Artefact | C4: Topic | D4: Key statement | E4: Provenance | F4: Verification status | G4: Basis | H4: Correction trail
A5: ST-01 | B5: CPS XXXX / CPG XXXX | C5: US legal status | D5: The United States model risk guidance is supervisory guidance and does not have the force and effect of law. | E5: Extracted | F5: Verified — primary source | G5: 12 CFR Part 4 Subpart F (OCC), 12 CFR §262.7 and Part 262 Appendix A (Board), 12 CFR Part 302 Subpart A (FDIC), codifying the 2018 interagency statement. SR 26-2 repeats the disclaimer on its face. | H5: None required.
A6: ST-02 | B6: All artefacts | C6: US currency | D6: OCC Bulletin 2011-12 and Federal Reserve SR 11-7 were rescinded and superseded on 17 April 2026 by SR 26-2, OCC Bulletin 2026-13 and FDIC FIL-15-2026. | E6: Extracted | F6: Verified — primary source | G6: SR 26-2 cover letter supersession statement; the four-item rescission list in OCC Bulletin 2026-13; FDIC FIL-15-2026; and the 'RESCINDED — Replaced, see OCC 2026-13' watermark on the OCC copy of the 2011 attachment. | H6: Corrected. The package initially cited SR 11-7 as current throughout. See RT-01.
A7: ST-03 | B7: CPS XXXX M02 | C7: US model definition | D7: The current US definition is narrower than the definition adopted in CPS XXXX and excludes spreadsheet arithmetic, deterministic rule-based processes, and generative and agentic AI. | E7: Extracted | F7: Verified — primary source | G7: SR 26-2 §II and footnote 3. | H7: Corrected. The draft initially attributed a broad three-part definition to current US guidance. See RT-02.
A8: ST-04 | B8: CPS XXXX M23 / CPG XXXX | C8: Effective challenge | D8: Effective challenge survives in the 2026 US guidance, reformulated around expertise, sufficient independence, and organisational standing and influence to effect change. | E8: Extracted | F8: Verified — primary source | G8: SR 26-2 §III. The rescinded 2011 formulation was a combination of incentives, competence and influence. | H8: Corrected. The draft initially used the 2011 formulation. See RT-03.
A9: ST-05 | B9: CPS XXXX M22 / CPG XXXX | C9: Components of validation | D9: The components of validation are conceptual soundness, outcomes analysis and ongoing model monitoring. | E9: Extracted | F9: Verified — primary source | G9: SR 26-2 §V, sub-headings 'Components of Model Validation', 'Conceptual Soundness', 'Outcomes Analysis', 'Ongoing Model Monitoring'. | H9: Corrected from the 2011 naming and ordering. See RT-04.
A10: ST-06 | B10: All artefacts | C10: PRA principle structure | D10: PRA SS1/23 has five principles and 23 sub-principles. Principle 5 is 'Model risk mitigants'. | E10: Extracted | F10: Verified — primary source | G10: SS1/23 primary text, principle and sub-principle headings transcribed verbatim. | H10: Corrected. A predecessor document in this project described Principle 5 as 'reporting'. See RT-05.
A11: ST-07 | B11: All artefacts | C11: OSFI structure | D11: OSFI Guideline E-23 (2027) is structured as three outcomes and twelve principles numbered 1.1 to 3.6. | E11: Extracted | F11: Verified — primary source | G11: E-23 (2027) sections A.5, B, C and D, principle headings transcribed verbatim. | H11: Corrected. A predecessor document described E-23 as having three outcomes only, which under-represents it by twelve citable units. See RT-06.
A12: ST-08 | B12: All artefacts | C12: OSFI status and scope | D12: E-23 (2027) was published on 11 September 2025 and takes effect on 1 May 2027. It covers banks, foreign bank branches, life and fraternal companies, property and casualty companies and trust and loan companies, and does not apply to federally regulated pension plans. | E12: Extracted | F12: Verified — primary source | G12: OSFI guidance library entry for E-23 (2027) and the covering letter. | H12: None required.
A13: ST-09 | B13: All artefacts | C13: ECB currency | D13: The ECB guide to internal models is at its June 2026 release, whose overarching principles chapter includes a section on implementation of a model risk management framework and a section on the use of machine learning techniques in internal models. | E13: Extracted | F13: Verified — primary source | G13: ECB guide to internal models, chapter and section headings. | H13: Corrected from an initial citation of the February 2024 release. See RT-07.
A14: ST-10 | B14: CPG XXXX Annex | C14: CRR binding articles | D14: The binding EU obligations on internal models sit in CRR Articles 174, 179, 185, 188, 189 and 191; the ECB guide interprets them and is not itself a legal act. | E14: Extracted | F14: Verified — primary source | G14: Regulation (EU) No 575/2013, article headings. | H14: None required.
A15: ST-11 | B15: All artefacts | C15: FSB status | D15: The FSB sound practices for responsible adoption of AI are a consultation report comprising twelve sound practices and are expressly not intended to establish an international standard. | E15: Extracted | F15: Verified — primary source | G15: FSB consultation report, sound practice headings and the report's own statement of status. | H15: None required.
... A22: ST-16 | B22: Workbook | C22: Validation frequencies | D22: The validation frequencies shown by tier are illustrative drafting, not derived from any comparator instrument. | E22: Policy choice | F22: Verified — primary source | G22: No comparator prescribes frequencies on a cross-industry basis; the rescinded 2011 US guidance contained an at-least-annual periodic review expectation which the 2026 guidance does not carry forward. | H22: Labelled as illustrative in both the guide and the workbook. See RT-10.

Sheet Red Team Audit
A1: Red-team challenge and correction audit
A2: POLICY DEVELOPMENT DRAFT — NOT IN FORCE | Preserves the statement as first drafted, the challenge made against it, the correction applied and the evidence. Items confirmed on challenge are retained so the record shows what was tested, not only what changed.
A4: ID | B4: Initial or challenged statement | C4: Challenge | D4: Correction applied | E4: Effect on outputs | F4: Evidence | G4: Severity | H4: Status
A5: RT-01 | B5: The package cited OCC Bulletin 2011-12 / Federal Reserve SR 11-7 as the current United States model risk guidance, and used it as the primary authority for thirty-three requirement citations. | C5: Is the 2011 guidance still current as at July 2026? Supervisory guidance is periodically revised and the drafter's knowledge may predate any revision. | D5: The 2011 guidance was rescinded and superseded on 17 April 2026 by interagency guidance issued as Federal Reserve SR 26-2, OCC Bulletin 2026-13 and FDIC FIL-15-2026. All citations were repointed to the 2026 guidance, the 2011 instrument was retained in the source register marked as rescinded for provenance, and the substantive divergences were assessed individually. | E5: Affected the source register, thirty-three requirement citations, sixteen guidance attribution lines and five scoring benchmarks. | F5: SR 26-2 cover letter; OCC Bulletin 2026-13 rescission list; FDIC FIL-15-2026; rescission watermark on the OCC copy of the 2011 attachment. | G5: High | H5: Closed — correction incorporated
A6: RT-02 | B6: CPS XXXX's model definition was presented as following the established three-part US formulation, implying current US support for a broad definition. | C6: Does the current US guidance still support a broad definition? If not, the standard is claiming alignment it does not have. | D6: The 2026 US guidance narrows the definition to a 'complex' quantitative method applying statistical, economic or financial theories and expressly excludes simple arithmetic such as spreadsheet calculations, deterministic rule-based processes, and generative and agentic AI. CPS XXXX retains the broad definition — deliberately, because the narrow one would exclude actuarial and unit pricing calculations central to the Australian cross-industry perimeter — and the divergence is now stated openly rather than concealed by a citation. | E6: M02 rewritten; its provenance changed from Extracted to Extracted + inferred; the benchmark authority for the definition domain moved from the US to the PRA and OSFI. | F6: SR 26-2 §II and footnote 3. | G6: High | H6: Closed — correction incorporated
A7: RT-03 | B7: Effective challenge was drafted as requiring 'competence, influence and incentive'. | C7: Is that the current formulation, or the rescinded one? | D7: That was the 2011 formulation. The 2026 guidance reformulates effective challenge around expertise to identify limitations, sufficient independence to maintain objectivity, and organisational standing and influence to effect change. M23 was redrafted to the current formulation; incentives are retained in the practice guide as a practical consideration rather than presented as part of the definition. | E7: M23 and the corresponding guidance paragraph rewritten. | F7: SR 26-2 §III; rescinded 2011 attachment §III for the superseded wording. | G7: Medium | H7: Closed — correction incorporated
A8: RT-04 | B8: Validation scope was drafted as 'conceptual soundness, ongoing monitoring including process verification and benchmarking, and outcomes analysis'. | C8: Are those the current component names and does benchmarking sit where the draft places it? | D8: The 2026 guidance names the components conceptual soundness, outcomes analysis and ongoing model monitoring, in that order, and locates benchmarking under conceptual soundness rather than ongoing monitoring. M22 and the guidance were realigned. | E8: M22 and two guidance paragraphs rewritten. | F8: SR 26-2 §V sub-headings. | G8: Medium | H8: Closed — correction incorporated
A9: RT-05 | B9: A predecessor document in this project described PRA SS1/23 Principle 5 as 'reporting'. | C9: Verify the five principle titles against the primary supervisory statement. | D9: Principle 5 is 'Model risk mitigants'. Reporting is embedded across the principles and is not a standalone principle. All five titles and all 23 sub-principle titles were transcribed verbatim from the primary text and carried into the principles register. | E9: Principles register, guidance attribution lines and the requirement-to-principle mapping. | F9: PRA SS1/23 primary text. | G9: High | H9: Closed — correction incorporated
A10: RT-06 | B10: A predecessor document described OSFI E-23 as having three outcomes. | C10: Is that the whole structure? A three-unit framework would be unusually sparse for a lifecycle guideline. | D10: E-23 (2027) is structured as three outcomes AND twelve principles numbered 1.1 to 3.6. Treating it as three citable units under-represents it by twelve. The full structure is now reproduced in the principles register and used for attribution. | E10: Principles register, crosswalk and requirement-to-principle mapping. | F10: OSFI E-23 (2027) sections A.5, B, C and D. | G10: High | H10: Closed — correction incorporated
A11: RT-07 | B11: The ECB guide to internal models was cited at its February 2024 release. | C11: Has the guide been revised since? | D11: The current release is June 2026. Its overarching principles chapter adds a section on implementation of a model risk management framework and a section on the use of machine learning techniques in internal models — both directly relevant to this standard and absent from the earlier release. The source register and the principles register were updated. | E11: Source register, principles register and two crosswalk cells. | F11: ECB guide to internal models, chapter and section headings. | G11: Medium | H11: Closed — correction incorporated
A12: RT-08 | B12: The BCBS third-party risk principles were cited as publication d588. | C12: Confirm the publication number and principle count. | D12: The principles are published as d605 and comprise twelve principles. The source register URL and the principle count were corrected, and the source moved from unverified to verified against the primary publication. | E12: Source register and principles register. | F12: BIS publication d605. | G12: Medium | H12: Closed — correction incorporated
A13: RT-09 | B13: An early draft proposed a model-risk-specific supervisory notification deadline. | C13: Is such a deadline supported by any comparator, and would it conflict with existing Australian notification architecture? | D13: No comparator imposes a model-specific notification deadline, and a new one risked conflicting with the materiality criteria and timeframes in CPS 230 and CPS 234. M45 now cross-references the existing architecture and expects early engagement on material model weakness instead. | E13: M45 redrafted; the notification domain scored against the existing architecture rather than a new obligation. | F13: CPS 230; CPS 234; comparator review. | G13: High | H13: Closed — correction incorporated
A14: RT-10 | B14: Validation frequencies by tier were presented in the practice guide without qualification. | C14: Are these frequencies drawn from any comparator instrument? | D14: They are not. The rescinded 2011 US guidance contained an at-least-annual periodic review expectation which the 2026 guidance does not carry forward, and the OCC has since confirmed that community banks are not required to validate annually. The table is now labelled as illustrative drafting and identified as a policy design choice. | E14: Practice guide validation table caption and verification annotation; statement ledger entry ST-16. | F14: OCC Bulletin 2025-26; SR 26-2 §V; rescinded 2011 attachment §V. | G14: Medium | H14: Closed — correction incorporated
A15: RT-11 | B15: An early draft required all models to be fully explainable. | C15: Is an absolute explainability requirement achievable, and is it supported? | D15: It is neither. Comparator authorities consistently frame explainability as fit for purpose and permit compensating controls where full explainability is not achievable. The guidance now requires explainability to be assessed against what the entity needs to do with the model, and requires outcome-based controls to be intensified where explainability is limited. | E15: Chapter 12 of the practice guide. | F15: Comparator review; ECB guide section on machine learning techniques. | G15: Medium | H15: Closed — correction incorporated
... A70: RT-18 | B70: The Comptroller's Handbook model risk management booklet was cited as a source. | C70: Is it retrievable, and is it current? | D70: It was rescinded on 17 April 2026 and its PDF no longer resolves on an official domain. Its existence, issuance and rescission are verified from two reachable OCC sources, but nothing about its contents is asserted anywhere in this package. | E70: Source register entry retained with a verification caveat; no requirement relies on it. | F70: OCC Bulletin 2021-39; OCC Bulletin 2026-13 rescission list. | G70: Low | H70: Closed — correction incorporated

Sheet Source Register
A1: Official source register
A2: POLICY DEVELOPMENT DRAFT — NOT IN FORCE | URLs point to official authority websites and were checked on the date shown.
A4: Source ID | B4: Authority | C4: Title | D4: Published | E4: Effective | F4: Legal status | G4: Relevant content | H4: Official URL | I4: Verification | J4: Checked
A5: US-MRM-2026 | B5: OCC / FRB / FDIC | C5: Supervisory Guidance on Model Risk Management — interagency guidance issued as Federal Reserve SR 26-2, OCC Bulletin 2026-13 and FDIC FIL-15-2026 | D5: 17 April 2026 | E5: 17 April 2026 | F5: Interagency supervisory guidance. Expressly non-enforceable: it 'does not set forth enforceable standards or prescriptive requirements' and non-compliance 'will not result in supervisory criticism'. US supervisory guidance does not have the force and effect of law. | G5: Current US framework. Seven sections: introduction; purpose and scope; overview of model risk and model risk management; model development and model use; model validation and monitoring; governance and controls; and vendor and other third-party products. Retains effective challenge and the three components of validation, and expressly addresses aggregate model risk. | H5: https://www.federalreserve.gov/supervisionreg/srletters/SR2602.htm | I5: Verified — primary source | J5: 25 Jul 2026
A6: US-MRM-2011 | B6: OCC / FRB | C6: OCC Bulletin 2011-12 / Federal Reserve SR 11-7 — Supervisory Guidance on Model Risk Management | D6: 4 April 2011 | E6: Rescinded and superseded 17 April 2026 | F6: Superseded supervisory guidance. Rescinded by OCC Bulletin 2026-13 and superseded by Federal Reserve SR 26-2 on 17 April 2026. Was never a regulation. Retained here for provenance because it originated most of the discipline's architecture. | G6: The originating framework: the three-component description of a model, the two sources of model risk, effective challenge, conceptual soundness, the three core elements of validation, inventory, documentation and vendor models. Its broad model definition is NOT carried forward into the 2026 guidance, which is narrower. | H6: https://www.occ.gov/static/rescinded-bulletins/bulletin-2011-12.pdf | I6: Verified — primary source | J6: 25 Jul 2026
A7: US-SG-STATUS | B7: OCC / FRB / FDIC | C7: Use of supervisory guidance — 12 CFR Part 4 Subpart F (OCC), 12 CFR §262.7 and Part 262 Appendix A (Board), 12 CFR Part 302 Appendix A (FDIC) | D7: Codified 2021, following the 2018 interagency statement | E7: In force | F7: Codified regulation. Binding on the agencies, not on supervised institutions. Provides that supervisory guidance does not have the force and effect of law and that the agencies do not take enforcement action on the basis of guidance. | G7: Establishes definitively that the US model risk guidance is not law. This is the single binding instrument in the US part of this evidence base, and it binds the regulators rather than the banks. | H7: https://www.ecfr.gov/current/title-12/chapter-I/part-4/subpart-F | I7: Verified — primary source | J7: 25 Jul 2026
A8: OCC-CB-2025 | B8: OCC | C8: OCC Bulletin 2025-26 — Model Risk Management: Clarification for Community Banks | D8: 6 October 2025 | E8: On issue | F8: Bulletin clarifying the application of existing supervisory guidance. Not a regulation. Not rescinded by OCC Bulletin 2026-13. | G8: States that OCC guidance does not require community banks to perform annual model validation, and that the OCC will not give negative supervisory feedback solely for the frequency or scope of validation a bank reasonably determined on a risk basis. Directly relevant to proportionality drafting. | H8: https://www.occ.gov/news-issuances/bulletins/2025/bulletin-2025-26.html | I8: Verified — primary source | J8: 25 Jul 2026
A9: OCC-HANDBOOK | B9: OCC | C9: Comptroller's Handbook — Model Risk Management booklet | D9: August 2021 | E9: Rescinded 17 April 2026 | F9: Examiner handbook booklet, rescinded by OCC Bulletin 2026-13. Was guidance for OCC examiners, not a regulation. | G9: Existence, issuance and rescission are confirmed. The booklet itself is no longer retrievable from an official domain and no statement about its contents is relied upon anywhere in this package. | H9: https://www.occ.gov/news-issuances/bulletins/2021/bulletin-2021-39.html | I9: Verified — secondary source | J9: 25 Jul 2026
A10: PRA-SS1-23 | B10: PRA | C10: SS1/23 — Model risk management principles for banks | D10: 17 May 2023; current version dated 16 April 2026 | E10: 17 May 2024 | F10: Supervisory statement setting out PRA expectations. Not a PRA Rulebook instrument and not binding law. | G10: Five principles with 23 sub-principles: model identification and model risk classification; governance; model development, implementation, and use; independent model validation; and model risk mitigants. | H10: https://www.bankofengland.co.uk/prudential-regulation/publication/2023/may/model-risk-management-principles-for-banks | I10: Verified — primary source | J10: 25 Jul 2026
A11: PRA-PS6-23 | B11: PRA | C11: PS6/23 — Model risk management principles for banks (Policy Statement) | D11: 17 May 2023 | E11: 17 May 2024 | F11: Policy statement. Explains the final policy and feedback; the operative expectations sit in SS1/23. | G11: Confirms the twelve-month implementation period and the restriction of scope to firms with internal model approval. | H11: https://www.bankofengland.co.uk/prudential-regulation/publication/2023/may/model-risk-management-principles-for-banks | I11: Verified — primary source | J11: 25 Jul 2026
A12: PRA-SS3-18 | B12: PRA | C12: SS3/18 — Model risk management principles for stress testing | D12: April 2018; current version dated April 2026 | E12: April 2018 | F12: Supervisory statement. PRA expectations, not binding law. | G12: Model risk management expectations specific to stress testing models, including governance of assumptions and expert judgement. | H12: https://www.bankofengland.co.uk/prudential-regulation/publication/2018/model-risk-management-principles-for-stress-testing-ss | I12: Verified — primary source | J12: 25 Jul 2026
A13: OSFI-E23 | B13: OSFI | C13: Guideline E-23 — Model Risk Management (2027) | D13: 11 September 2025 | E13: 1 May 2027 | F13: Final supervisory guideline. Not yet in effect at the as-of date. Sound Business and Financial Practices category. | G13: Three outcomes and twelve principles numbered 1.1 to 3.6, covering enterprise-wide model risk management, a risk-based approach, and model lifecycle management. Appendix 1, Information tracking for models, sets out minimum model inventory content. Expressly covers AI and machine learning models. | H13: https://www.osfi-bsif.gc.ca/en/guidance/guidance-library/guideline-e-23-model-risk-management-2027 | I13: Verified — primary source | J13: 25 Jul 2026
A14: OSFI-E23-2017 | B14: OSFI | C14: Guideline E-23 — Enterprise-Wide Model Risk Management for Deposit-Taking Institutions (2017) | D14: 30 September 2017 | E14: On issue | F14: Supervisory guideline. OSFI's guidance library presents the 2027 guideline as its replacement from 1 May 2027, but no express supersession clause was located in either the 2027 guideline or its covering letter, so the relationship is stated as OSFI presents it rather than as a quoted provision. | G14: The predecessor framework, structured as numbered sections rather than principles. Included for contrast with the expanded 2027 scope. | H14: https://www.osfi-bsif.gc.ca/en/guidance/guidance-library/enterprise-wide-model-risk-management-deposit-taking-institutions | I14: Verified — primary source | J14: 25 Jul 2026
A15: OSFI-B10 | B15: OSFI | C15: Guideline B-10 — Third-Party Risk Management | D15: April 2023 | E15: 1 May 2024 | F15: Supervisory guideline. | G15: Third-party arrangements including externally supplied models and the information rights needed to govern them. | H15: https://www.osfi-bsif.gc.ca/en/guidance/guidance-library/third-party-risk-management-guideline | I15: Verified — primary source | J15: 25 Jul 2026
... A54: APRA-SPS515 | B54: APRA | C54: Prudential Standard SPS 515 Strategic Planning and Member Outcomes | D54: Current at the as-of date | E54: In force at the as-of date | F54: Binding prudential standard. | G54: Business performance review and member outcomes assessment, which rely on modelled projections. | H54: https://www.apra.gov.au/standards/sps-515 | I54: Verified — primary source | J54: 25 Jul 2026

Sheet Glossary
A1: Glossary and provenance terms
A2: POLICY DEVELOPMENT DRAFT — NOT IN FORCE | Draft definitions require legal alignment before issue.
A4: Term | B4: Definition
A5: Model | B5: A quantitative method, system or approach that applies statistical, economic, financial, actuarial or mathematical theories, techniques or assumptions to process input data into quantitative estimates.
A6: Model risk | B6: The potential for adverse consequences from decisions based on incorrect or misused model outputs. Model risk arises where a model has fundamental errors and produces inaccurate outputs relative to its design objective and intended use, or where a model is used incorrectly or inappropriately.
A7: Material model | B7: A model that is used for a material purpose, or whose failure or misuse could otherwise have a material effect on the entity's financial position, its regulatory obligations, its critical operations, or amounts or entitlements attributable to its customers or beneficiaries.
A8: Model owner | B8: The person accountable for a model being fit for its approved purpose throughout its lifecycle, including its documentation, performance monitoring, communication of limitations and remediation of findings.
A9: Model risk tier | B9: The classification assigned to a model under the entity's tiering methodology, which determines the intensity of controls applied to it.
A10: Independent validation | B10: An assessment of a model's fitness for its intended use performed by persons who did not develop the model and who are not accountable to those who developed it or who sponsor its use.
A11: Effective challenge | B11: Critical and objective analysis by persons with the expertise to identify model limitations, sufficient independence to maintain objectivity, and the organisational standing and influence to effect change.
A12: Conceptual soundness | B12: The quality of a model's design, theory, methodology and assumptions as appropriate for the purpose for which the model will be used.
A13: Outcomes analysis | B13: Comparison of model outputs with corresponding actual outcomes, used to assess whether a model continues to perform as intended.
A14: Overlay | B14: An adjustment applied to a model's output before it is used, including management overlays, post-model adjustments and model overrides.
A15: Quantitative decision tool | B15: A quantitative method that materially informs a decision but does not meet the definition of a model.
... A29: Unverified — not independently confirmed | B29: Could not be confirmed from an official source and is not relied upon for any statement of requirement.
